{
  "level": "Level B",
  "part": "Henry's Hike",
  "sections": [
    {
      "section": "Henry's Hike",
      "tree": {
        "id": "root",
        "text": "Henry's Hike",
        "emoji": "🥾",
        "children": [
          {
            "id": "intro",
            "text": "Introduction",
            "emoji": "📖",
            "children": [
              {
                "id": "intro_1",
                "text": "Henry hikes into the park.",
                "cn": "亨利徒步走进公园。",
                "notes": "hikes: 徒步旅行；into: 进入……里面。",
                "statement": "这句话描述了亨利正在离开公园。",
                "answer": false,
                "explanation": "into 表示进入，所以是走进公园。",
                "emoji": "🌳",
                "keywords": "hikes, park",
                "highlight": "hikes into",
                "children": []
              }
            ]
          },
          {
            "id": "journey",
            "text": "The Journey",
            "emoji": "🗺️",
            "children": [
              {
                "id": "j_1",
                "text": "Henry hikes on the trail.",
                "cn": "亨利在小路上徒步。",
                "notes": "trail: 小路、路径。",
                "statement": "trail 指的是宽阔的马路。",
                "answer": false,
                "explanation": "trail 通常指林间或山间的小路。",
                "emoji": "🛤️",
                "keywords": "hikes, trail",
                "children": []
              },
              {
                "id": "j_2",
                "text": "Henry hikes around the pond.",
                "cn": "亨利绕着池塘徒步。",
                "notes": "around: 绕着、环绕。",
                "statement": "around 在这里表示环绕的意思。",
                "answer": true,
                "explanation": "around the pond 表示沿着池塘周围走。",
                "emoji": "🦆",
                "keywords": "hikes, pond",
                "highlight": "around",
                "children": []
              },
              {
                "id": "j_3",
                "text": "Henry hikes in the mud.",
                "cn": "亨利在泥地里徒步。",
                "notes": "mud: 泥、泥浆。",
                "statement": "mud 是指干净的草地。",
                "answer": false,
                "explanation": "mud 的意思是泥巴。",
                "emoji": "👣",
                "keywords": "hikes, mud",
                "children": []
              },
              {
                "id": "j_4",
                "text": "Henry hikes up the hill.",
                "cn": "亨利徒步上山。",
                "notes": "up: 向上。",
                "statement": "up the hill 表示往山上走。",
                "answer": true,
                "explanation": "up 表示方向向上。",
                "emoji": "⛰️",
                "keywords": "hikes, hill",
                "highlight": "up",
                "children": []
              },
              {
                "id": "j_5",
                "text": "Henry hikes past the deer.",
                "cn": "亨利徒步经过鹿群。",
                "notes": "past: 经过；deer: 鹿（单复数同形）。",
                "statement": "past 在这里是动词。",
                "answer": false,
                "explanation": "past 在这里是介词，表示经过。",
                "emoji": "🦌",
                "keywords": "hikes, past, deer",
                "highlight": "past",
                "children": []
              },
              {
                "id": "j_6",
                "text": "Henry hikes down the hill.",
                "cn": "亨利徒步下山。",
                "notes": "down: 向下。",
                "statement": "down the hill 表示往山下走。",
                "answer": true,
                "explanation": "down 表示方向向下。",
                "emoji": "📉",
                "keywords": "hikes, down, hill",
                "highlight": "down",
                "children": []
              }
            ]
          },
          {
            "id": "conclusion",
            "text": "Conclusion",
            "emoji": "🏁",
            "children": [
              {
                "id": "c_1",
                "text": "Henry hikes to the car.",
                "cn": "亨利徒步走到车旁。",
                "notes": "to: 到……去。",
                "statement": "to 表示目的地。",
                "answer": true,
                "explanation": "to the car 表示目的地是车。",
                "emoji": "🚗",
                "keywords": "hikes, car",
                "highlight": "to",
                "children": []
              }
            ]
          }
        ]
      }
    }
  ]
}