{
  "level": "Grade 8 Semester 1",
  "part": "Unit 2",
  "section": "Section B Activity 1b",
  "tree": {
    "id": "root",
    "text": "Going Home for the Spring Festival",
    "emoji": "🚂",
    "children": [
      {
        "id": "c1_trip",
        "text": "The Journey",
        "emoji": "✈️",
        "children": [
          {
            "id": "s1",
            "text": "\"It's almost the Spring Festival. Can we go to Hainan for the holiday, Dad?\"",
            "emoji": "🏝️",
            "keywords": "Spring Festival, Hainan, holiday",
            "cn": "“快过春节了。爸爸，我们能去海南度假吗？”",
            "statement": "孩子询问爸爸是否能在春节去海南度假。",
            "answer": true,
            "explanation": "句子中表达了询问去海南度假的想法。陈述正确。",
            "children": [
              {
                "id": "s2",
                "text": "\"Not this time,\" Dad answered with a smile. \"We're going to your mum's hometown!\"",
                "emoji": "👵",
                "highlight": "with",
                "keywords": "Not this time, hometown",
                "cn": "“这次不行，”爸爸微笑着回答。“我们要去你妈妈的故乡！”",
                "statement": "他们决定去海南度假。",
                "answer": false,
                "explanation": "爸爸说 'Not this time'（这次不行），他们要去的是妈妈的故乡（mum's hometown），不是海南。因此陈述是错误的。",
                "children": []
              }
            ]
          },
          {
            "id": "s3",
            "text": "Soon the day of our family trip came. We got up very early in the morning to catch the train.",
            "emoji": "🌅",
            "keywords": "got up, catch train",
            "cn": "很快，我们家庭旅行的日子到了。我们早上起得很早去赶火车。",
            "statement": "'get up' 过去式为 'got up'，'to catch the train' 不定式作目的状语。",
            "answer": true,
            "explanation": "动词 get 的过去式是 got；to catch the train 是动词不定式，在句中作目的状语，表示“为了赶火车”。陈述正确。",
            "children": [
              {
                "id": "s4",
                "text": "The train journey took more than five hours, and then we changed to a bus to get to my grandparents' village in the afternoon.",
                "emoji": "🚌",
                "highlight": "more than, and then",
                "keywords": "journey, five hours, changed bus",
                "cn": "火车旅程花了五个多小时，然后我们在下午转乘公共汽车前往我祖父母的村庄。",
                "statement": "坐火车旅行花了不到五个小时。",
                "answer": false,
                "explanation": "文中提到 'took more than five hours'（花了五个多小时），而不是不到五个小时。因此陈述是错误的。",
                "children": []
              }
            ]
          }
        ]
      },
      {
        "id": "c2_arrival",
        "text": "The Arrival",
        "emoji": "🏡",
        "children": [
          {
            "id": "s5",
            "text": "At the end of the road, I saw Grandpa and my little cousin standing in the cold wind waiting for us.",
            "emoji": "🌬️",
            "keywords": "saw, Grandpa, cousin, waiting",
            "cn": "在路的尽头，我看到爷爷和小表弟站在寒风中等我们。",
            "statement": "爷爷和表弟在暖和的屋里等着他们。",
            "answer": false,
            "explanation": "他们站在寒风（cold wind）中等待，因此是在户外。陈述是错误的。",
            "children": [
              {
                "id": "s6",
                "text": "We walked quickly to greet them. Grandpa helped us pull the heavy luggage into the house.",
                "emoji": "🧳",
                "keywords": "greet, heavy luggage",
                "cn": "我们快步走过去迎接他们。爷爷帮我们把沉重的行李拉进屋里。",
                "statement": "爷爷帮助他们搬了行李。",
                "answer": true,
                "explanation": "爷爷帮助他们把沉重的行李拉进了屋里（'helped us pull the heavy luggage'）。陈述正确。",
                "children": [
                  {
                    "id": "s7",
                    "text": "\"Ah, home again!\" said Mum with a smile on her face.",
                    "emoji": "😊",
                    "highlight": "with",
                    "keywords": "home again, smile",
                    "cn": "“啊，又到家了！”妈妈脸上带着微笑说道。",
                    "statement": "回到故乡，妈妈感到很伤心。",
                    "answer": false,
                    "explanation": "妈妈是带着微笑（'with a smile'）说 'home again!'，感到温暖亲切，并非伤心。因此陈述是错误的。",
                    "children": []
                  }
                ]
              }
            ]
          }
        ]
      },
      {
        "id": "c3_dinner",
        "text": "Dinner Time",
        "emoji": "🍲",
        "children": [
          {
            "id": "s8",
            "text": "Grandma, my aunt, and my uncle were busy cooking dinner in the kitchen. They were very happy to see us.",
            "emoji": "🧑‍🍳",
            "keywords": "busy cooking, happy",
            "cn": "奶奶、婶婶和叔叔正忙着在厨房做饭。他们看到我们非常高兴。",
            "statement": "'be busy doing sth' 意为“忙于做某事”。",
            "answer": true,
            "explanation": "固定搭配 'be busy doing sth' 表示忙着做某事，这里是 'were busy cooking'。陈述正确。",
            "children": [
              {
                "id": "s9",
                "text": "\"Could you bring Wenwen her favourite snacks?\" Grandma asked Grandpa.",
                "emoji": "🍪",
                "keywords": "bring, snacks",
                "cn": "“你能给雯雯拿她最喜欢的零食吗？”奶奶问爷爷。",
                "statement": "奶奶请求爷爷给雯雯拿零食。",
                "answer": true,
                "explanation": "奶奶问爷爷 'Could you bring Wenwen her favourite snacks?'，属于委婉请求。陈述正确。",
                "children": [
                  {
                    "id": "s10",
                    "text": "I shared the snacks with my cousin and told Grandpa about school. He was happy to hear I was doing well at school.",
                    "emoji": "🏫",
                    "keywords": "shared snacks, cousin, Grandpa",
                    "cn": "我和表弟分享了零食，并跟爷爷讲了学校里的事。听到我在学校表现很好，他很高兴。",
                    "statement": "作者独自吃完了所有零食，没有分享。",
                    "answer": false,
                    "explanation": "文中写到 'I shared the snacks with my cousin'（我和我的表弟分享了零食）。因此陈述是错误的。",
                    "children": []
                  }
                ]
              }
            ]
          },
          {
            "id": "s11",
            "text": "We then enjoyed all the delicious food. \"Mm, the familiar taste of home!\" said Mum.",
            "emoji": "😋",
            "keywords": "delicious food, familiar taste",
            "cn": "然后我们享用了所有美味的食物。“嗯，这熟悉的家的味道！”妈妈说。",
            "statement": "'delicious' 意为“美味的”，'familiar' 意为“熟悉的”。",
            "answer": true,
            "explanation": "这两个词的中文意思分别是：delicious美味的，familiar熟悉的。陈述正确。",
            "children": [
              {
                "id": "s12",
                "text": "During the dinner, my uncle told us some jokes and we had a good laugh.",
                "emoji": "😆",
                "highlight": "During",
                "keywords": "jokes, laugh",
                "cn": "晚餐期间，我叔叔给我们讲了一些笑话，我们开怀大笑。",
                "statement": "晚餐时气氛非常沉闷严肃。",
                "answer": false,
                "explanation": "叔叔讲了笑话，大家开怀大笑（'had a good laugh'），说明气氛很欢乐愉快，不沉闷。因此陈述是错误的。",
                "children": []
              }
            ]
          }
        ]
      },
      {
        "id": "c4_leaving",
        "text": "The Departure",
        "emoji": "👋",
        "children": [
          {
            "id": "s13",
            "text": "Several days later when we were leaving, Grandma held my hands and asked us, \"Will you come home more often?\"",
            "emoji": "👵",
            "keywords": "leaving, held hands, more often",
            "cn": "几天后我们要走的时候，奶奶握着我的手问我们：“你们能常回家看看吗？”",
            "statement": "奶奶舍不得他们走，希望他们多回家。",
            "answer": true,
            "explanation": "奶奶拉着手问 'Will you come home more often?'，体现了对晚辈依依不舍与期盼。陈述正确。",
            "children": [
              {
                "id": "s14",
                "text": "Mum nodded, with tears in her eyes.",
                "emoji": "😢",
                "highlight": "with",
                "keywords": "nodded, tears",
                "cn": "妈妈点点头，眼里含着泪水。",
                "statement": "妈妈在摇头表示拒绝。",
                "answer": false,
                "explanation": "妈妈是 'nodded'（点头），而不是摇头。因此陈述是错误的。",
                "children": []
              }
            ]
          }
        ]
      }
    ]
  }
}
