{
  "level": "Grade 3 Semester 2 - Unit 5",
  "title": "Spelling Master",
  "spelling_words": [
    {
      "id": "0b4f5147",
      "word": "tell",
      "meaning": "告诉",
      "type": "single-syllable",
      "chunks": [
        {
          "correct": "t",
          "options": [
            "t",
            "d",
            "p"
          ]
        },
        {
          "correct": "e",
          "options": [
            "e",
            "a",
            "i"
          ]
        },
        {
          "correct": "ll",
          "options": [
            "ll",
            "rl",
            "l"
          ]
        }
      ]
    },
    {
      "id": "bb64d4fb",
      "word": "clock",
      "meaning": "时钟",
      "type": "single-syllable",
      "chunks": [
        {
          "correct": "cl",
          "options": [
            "gl",
            "kl",
            "cl"
          ]
        },
        {
          "correct": "o",
          "options": [
            "u",
            "o",
            "a"
          ]
        },
        {
          "correct": "ck",
          "options": [
            "ck",
            "ke",
            "k"
          ]
        }
      ]
    },
    {
      "id": "481160cd",
      "word": "fifteen",
      "meaning": "十五",
      "type": "multi-syllable",
      "chunks": [
        {
          "correct": "fif",
          "options": [
            "fef",
            "fiv",
            "fif"
          ]
        },
        {
          "correct": "teen",
          "options": [
            "ten",
            "teen",
            "tain"
          ]
        }
      ]
    },
    {
      "id": "45c46513",
      "word": "thirty",
      "meaning": "三十",
      "type": "multi-syllable",
      "chunks": [
        {
          "correct": "thir",
          "options": [
            "thir",
            "thur",
            "ther"
          ]
        },
        {
          "correct": "ty",
          "options": [
            "ty",
            "tie",
            "tee"
          ]
        }
      ]
    },
    {
      "id": "323bc542",
      "word": "dinner",
      "meaning": "正餐",
      "type": "multi-syllable",
      "chunks": [
        {
          "correct": "din",
          "options": [
            "din",
            "dan",
            "den"
          ]
        },
        {
          "correct": "ner",
          "options": [
            "nar",
            "ner",
            "nor"
          ]
        }
      ]
    },
    {
      "id": "8cf8d32e",
      "word": "half",
      "meaning": "一半",
      "type": "single-syllable",
      "chunks": [
        {
          "correct": "h",
          "options": [
            "l",
            "f",
            "h"
          ]
        },
        {
          "correct": "a",
          "options": [
            "a",
            "o",
            "u"
          ]
        },
        {
          "correct": "lf",
          "options": [
            "lf",
            "ve",
            "fe"
          ]
        }
      ]
    },
    {
      "id": "504a7727",
      "word": "past",
      "meaning": "晚于",
      "type": "single-syllable",
      "chunks": [
        {
          "correct": "p",
          "options": [
            "b",
            "p",
            "t"
          ]
        },
        {
          "correct": "a",
          "options": [
            "a",
            "e",
            "u"
          ]
        },
        {
          "correct": "st",
          "options": [
            "ts",
            "st",
            "sd"
          ]
        }
      ]
    },
    {
      "id": "41ef3c98",
      "word": "homework",
      "meaning": "家庭作业",
      "type": "multi-syllable",
      "chunks": [
        {
          "correct": "home",
          "options": [
            "hope",
            "hose",
            "home"
          ]
        },
        {
          "correct": "work",
          "options": [
            "walk",
            "word",
            "work"
          ]
        }
      ]
    },
    {
      "id": "00d997ab",
      "word": "need",
      "meaning": "需要",
      "type": "single-syllable",
      "chunks": [
        {
          "correct": "n",
          "options": [
            "m",
            "l",
            "n"
          ]
        },
        {
          "correct": "ee",
          "options": [
            "e",
            "ea",
            "ee"
          ]
        },
        {
          "correct": "d",
          "options": [
            "d",
            "b",
            "t"
          ]
        }
      ]
    },
    {
      "id": "fdf8f27b",
      "word": "activity",
      "meaning": "活动",
      "type": "multi-syllable",
      "chunks": [
        {
          "correct": "ac",
          "options": [
            "ac",
            "ec",
            "ic"
          ]
        },
        {
          "correct": "tiv",
          "options": [
            "tuv",
            "tiv",
            "tev"
          ]
        },
        {
          "correct": "i",
          "options": [
            "e",
            "i",
            "a"
          ]
        },
        {
          "correct": "ty",
          "options": [
            "ty",
            "tie",
            "tee"
          ]
        }
      ]
    },
    {
      "id": "1c6fe18d",
      "word": "evening",
      "meaning": "晚上",
      "type": "multi-syllable",
      "chunks": [
        {
          "correct": "eve",
          "options": [
            "evi",
            "eve",
            "eva"
          ]
        },
        {
          "correct": "ning",
          "options": [
            "ning",
            "mang",
            "neng"
          ]
        }
      ]
    },
    {
      "id": "e582b883",
      "word": "class",
      "meaning": "课",
      "type": "single-syllable",
      "chunks": [
        {
          "correct": "cl",
          "options": [
            "gl",
            "cl",
            "kl"
          ]
        },
        {
          "correct": "a",
          "options": [
            "a",
            "e",
            "u"
          ]
        },
        {
          "correct": "ss",
          "options": [
            "ss",
            "st",
            "s"
          ]
        }
      ]
    },
    {
      "id": "4db48662",
      "word": "call",
      "meaning": "打电话",
      "type": "single-syllable",
      "chunks": [
        {
          "correct": "c",
          "options": [
            "k",
            "c",
            "g"
          ]
        },
        {
          "correct": "a",
          "options": [
            "o",
            "a",
            "u"
          ]
        },
        {
          "correct": "ll",
          "options": [
            "ll",
            "rl",
            "l"
          ]
        }
      ]
    },
    {
      "word": "tick-tock",
      "meaning": "嘀嗒声",
      "type": "multi-syllable",
      "chunks": [
        {
          "correct": "tick",
          "options": [
            "teck",
            "tick",
            "tyck"
          ]
        },
        {
          "correct": "-",
          "options": [
            "-",
            "~",
            "_"
          ]
        },
        {
          "correct": "tock",
          "options": [
            "tuck",
            "tock",
            "tack"
          ]
        }
      ],
      "id": "b9b3b111"
    },
    {
      "word": "o'clock",
      "meaning": "…………点钟",
      "type": "multi-syllable",
      "chunks": [
        {
          "correct": "o'",
          "options": [
            "u'",
            "a'",
            "o'"
          ]
        },
        {
          "correct": "clock",
          "options": [
            "clack",
            "cluck",
            "clock"
          ]
        }
      ],
      "id": "e44f96d3"
    },
    {
      "word": "forty-five",
      "meaning": "四十五",
      "type": "multi-syllable",
      "chunks": [
        {
          "correct": "for",
          "options": [
            "for",
            "fer",
            "far"
          ]
        },
        {
          "correct": "ty",
          "options": [
            "ty",
            "tey",
            "ti"
          ]
        },
        {
          "correct": "-",
          "options": [
            "_",
            "~",
            "-"
          ]
        },
        {
          "correct": "five",
          "options": [
            "vive",
            "five",
            "fife"
          ]
        }
      ],
      "id": "28d8b86d"
    },
    {
      "word": "urgh",
      "meaning": "呀,哎呀",
      "type": "single-syllable",
      "chunks": [
        {
          "correct": "ur",
          "options": [
            "ir",
            "ur",
            "er"
          ]
        },
        {
          "correct": "gh",
          "options": [
            "ph",
            "ch",
            "gh"
          ]
        }
      ],
      "id": "c5e7d51d"
    },
    {
      "word": "her",
      "meaning": "她的",
      "type": "single-syllable",
      "chunks": [
        {
          "correct": "h",
          "options": [
            "f",
            "h",
            "w"
          ]
        },
        {
          "correct": "er",
          "options": [
            "ur",
            "ar",
            "er"
          ]
        }
      ],
      "id": "4486fa42"
    }
  ]
}