{
  "level": "Grade 5 Semester 2 - Unit 3",
  "title": "Spelling Master",
  "spelling_words": [
    {
      "word": "adventure",
      "meaning": "历险(经历); 奇遇",
      "type": "multi-syllable",
      "chunks": [
        { "correct": "ad", "options": ["ad", "ed", "od"] },
        { "correct": "ven", "options": ["ven", "van", "vin"] },
        { "correct": "ture", "options": ["ture", "cher", "sure"] }
      ]
    },
    {
      "word": "history",
      "meaning": "历史",
      "type": "multi-syllable",
      "chunks": [
        { "correct": "his", "options": ["his", "hes", "has"] },
        { "correct": "to", "options": ["to", "ta", "tu"] },
        { "correct": "ry", "options": ["ry", "rey", "rie"] }
      ]
    },
    {
      "word": "mystery",
      "meaning": "悬疑故事",
      "type": "multi-syllable",
      "chunks": [
        { "correct": "mys", "options": ["mys", "mis", "mes"] },
        { "correct": "te", "options": ["te", "ty", "ti"] },
        { "correct": "ry", "options": ["ry", "ley", "dy"] }
      ]
    },
    {
      "word": "fantasy",
      "meaning": "幻想作品",
      "type": "multi-syllable",
      "chunks": [
        { "correct": "fan", "options": ["fan", "fun", "fen"] },
        { "correct": "ta", "options": ["ta", "te", "to"] },
        { "correct": "sy", "options": ["sy", "cy", "zy"] }
      ]
    },
    {
      "word": "journey",
      "meaning": "旅行, 旅程",
      "type": "multi-syllable",
      "chunks": [
        { "correct": "jour", "options": ["jour", "ger", "jur"] },
        { "correct": "ney", "options": ["ney", "ny", "ni"] }
      ]
    },
    {
      "word": "west",
      "meaning": "西, 西面",
      "type": "single-syllable",
      "chunks": [
        { "correct": "w", "options": ["w", "v", "u"] },
        { "correct": "e", "options": ["e", "a", "i"] },
        { "correct": "st", "options": ["st", "ts", "sd"] }
      ]
    },
    {
      "word": "thousand",
      "meaning": "一千",
      "type": "multi-syllable",
      "chunks": [
        { "correct": "thou", "options": ["thou", "thaw", "thoo"] },
        { "correct": "sand", "options": ["sand", "send", "sond"] }
      ]
    },
    {
      "word": "nation",
      "meaning": "民族",
      "type": "multi-syllable",
      "chunks": [
        { "correct": "na", "options": ["na", "ne", "ni"] },
        { "correct": "tion", "options": ["tion", "sion", "shun"] }
      ]
    },
    {
      "word": "horseback",
      "meaning": "马背",
      "type": "multi-syllable",
      "chunks": [
        { "correct": "horse", "options": ["horse", "house", "hose"] },
        { "correct": "back", "options": ["back", "beck", "bank"] }
      ]
    },
    {
      "word": "horse",
      "meaning": "马",
      "type": "single-syllable",
      "chunks": [
        { "correct": "h", "options": ["h", "k", "n"] },
        { "correct": "or", "options": ["or", "ar", "er"] },
        { "correct": "se", "options": ["se", "ce", "ze"] }
      ]
    },
    {
      "word": "librarian",
      "meaning": "图书管理员",
      "type": "multi-syllable",
      "chunks": [
        { "correct": "li", "options": ["li", "ly", "le"] },
        { "correct": "brar", "options": ["brar", "brer", "brir"] },
        { "correct": "i", "options": ["i", "e", "y"] },
        { "correct": "an", "options": ["an", "en", "un"] }
      ]
    },
    {
      "word": "secret",
      "meaning": "秘密的",
      "type": "multi-syllable",
      "chunks": [
        { "correct": "se", "options": ["se", "si", "ce"] },
        { "correct": "cret", "options": ["cret", "crit", "creat"] }
      ]
    },
    {
      "word": "title",
      "meaning": "标题",
      "type": "multi-syllable",
      "chunks": [
        { "correct": "ti", "options": ["ti", "ty", "te"] },
        { "correct": "tle", "options": ["tle", "tal", "tel"] }
      ]
    },
    {
      "word": "cousin",
      "meaning": "堂(表)兄弟",
      "type": "multi-syllable",
      "chunks": [
        { "correct": "cou", "options": ["cou", "cau", "cu"] },
        { "correct": "sin", "options": ["sin", "sen", "son"] }
      ]
    },
    {
      "word": "friendly",
      "meaning": "友好的",
      "type": "multi-syllable",
      "chunks": [
        { "correct": "friend", "options": ["friend", "freind", "frand"] },
        { "correct": "ly", "options": ["ly", "ley", "li"] }
      ]
    },
    {
      "word": "nature",
      "meaning": "大自然",
      "type": "multi-syllable",
      "chunks": [
        { "correct": "na", "options": ["na", "ne", "no"] },
        { "correct": "ture", "options": ["ture", "cher", "sure"] }
      ]
    },
    {
      "word": "would",
      "meaning": "愿意",
      "type": "single-syllable",
      "chunks": [
        { "correct": "w", "options": ["w", "v", "l"] },
        { "correct": "ou", "options": ["ou", "u", "o"] },
        { "correct": "ld", "options": ["ld", "lt", "rd"] }
      ]
    },
    {
      "word": "pair",
      "meaning": "一对",
      "type": "single-syllable",
      "chunks": [
        { "correct": "p", "options": ["p", "b", "f"] },
        { "correct": "air", "options": ["air", "are", "ear"] }
      ]
    },
    {
      "word": "building",
      "meaning": "建筑物",
      "type": "multi-syllable",
      "chunks": [
        { "correct": "build", "options": ["build", "biuld", "biled"] },
        { "correct": "ing", "options": ["ing", "eng", "ung"] }
      ]
    },
    {
      "word": "air",
      "meaning": "空中",
      "type": "single-syllable",
      "chunks": [
        { "correct": "air", "options": ["air", "are", "ear"] }
      ]
    },
    {
      "word": "British",
      "meaning": "英国的",
      "type": "multi-syllable",
      "chunks": [
        { "correct": "Brit", "options": ["Brit", "Bret", "Brat"] },
        { "correct": "ish", "options": ["ish", "esh", "ash"] }
      ]
    },
    {
      "word": "science",
      "meaning": "科学",
      "type": "multi-syllable",
      "chunks": [
        { "correct": "sci", "options": ["sci", "si", "cy"] },
        { "correct": "ence", "options": ["ence", "ance", "ince"] }
      ]
    },
    {
      "word": "fiction",
      "meaning": "小说",
      "type": "multi-syllable",
      "chunks": [
        { "correct": "fic", "options": ["fic", "fec", "fac"] },
        { "correct": "tion", "options": ["tion", "sion", "shun"] }
      ]
    },
    {
      "word": "character",
      "meaning": "角色",
      "type": "multi-syllable",
      "chunks": [
        { "correct": "char", "options": ["char", "car", "shar"] },
        { "correct": "ac", "options": ["ac", "ec", "ic"] },
        { "correct": "ter", "options": ["ter", "tar", "tor"] }
      ]
    },
    {
      "word": "suggest",
      "meaning": "建议",
      "type": "multi-syllable",
      "chunks": [
        { "correct": "sug", "options": ["sug", "sag", "seg"] },
        { "correct": "gest", "options": ["gest", "gast", "gist"] }
      ]
    },
    {
      "word": "difficult",
      "meaning": "困难的",
      "type": "multi-syllable",
      "chunks": [
        { "correct": "dif", "options": ["dif", "def", "daf"] },
        { "correct": "fi", "options": ["fi", "fy", "fe"] },
        { "correct": "cult", "options": ["cult", "colt", "kalt"] }
      ]
    },
    {
      "word": "celebrate",
      "meaning": "庆祝",
      "type": "multi-syllable",
      "chunks": [
        { "correct": "cel", "options": ["cel", "cal", "sel"] },
        { "correct": "e", "options": ["e", "a", "i"] },
        { "correct": "brate", "options": ["brate", "brite", "brete"] }
      ]
    },
    {
      "word": "bookmark",
      "meaning": "书签",
      "type": "multi-syllable",
      "chunks": [
        { "correct": "book", "options": ["book", "buck", "boak"] },
        { "correct": "mark", "options": ["mark", "merk", "mork"] }
      ]
    }
  ]
}
