{
  "title": "After School",
  "level": "Level B - Sentence Architect",
  "ID_A": "3a4X5y2B1mL6p0Q",
  "primaryColor": "#58cc02",
  "primaryColorDark": "#46a302",
  "storageSuffix": "_afterschool",
  "passcode": "AFTER",
  "ipaDict": {
    "school": "skuːl",
    "study": "ˈstʌdi",
    "play": "pleɪ",
    "dance": "dɑːns",
    "act": "ækt",
    "read": "riːd",
    "sing": "sɪŋ",
    "bike": "baɪk",
    "fun": "fʌn",
    "friends": "frendz",
    "library": "ˈlaɪbrəri",
    "football": "ˈfʊtbɔːl"
  },
  "challenges": [
    {
      "id": "c1",
      "title": "Action Time",
      "icon": "🏃‍♂️",
      "data": [
        {
          "en": "I like to study after school.",
          "cn": "我喜欢放学后学习。",
          "hint": "after school / 放学后",
          "noise": [
            "likes",
            "studying"
          ],
          "accept": [
            "After school I like to study."
          ],
          "id": "22e43152"
        },
        {
          "en": "I like to play after school.",
          "cn": "我喜欢放学后玩耍。",
          "hint": "like to + verb / 喜欢做某事",
          "noise": [
            "playing",
            "am"
          ],
          "accept": [
            "After school I like to play."
          ],
          "id": "f7b75677"
        },
        {
          "en": "I like to dance after school.",
          "cn": "我喜欢放学后跳舞。",
          "hint": "action: dance / 动作：跳舞",
          "noise": [
            "dances",
            "do"
          ],
          "accept": [
            "After school I like to dance."
          ],
          "id": "8c2eae7f"
        },
        {
          "en": "I like to act after school.",
          "cn": "我喜欢放学后表演。",
          "hint": "action: act / 动作：表演",
          "noise": [
            "acts",
            "acting"
          ],
          "accept": [
            "After school I like to act."
          ],
          "id": "8f35d14b"
        },
        {
          "en": "We like to study after school.",
          "cn": "我们喜欢放学后学习。",
          "hint": "we = us / 我们",
          "noise": [
            "us",
            "studying"
          ],
          "accept": [
            "After school we like to study."
          ],
          "id": "a15740e5"
        },
        {
          "en": "We like to play after school.",
          "cn": "我们喜欢放学后玩耍。",
          "hint": "like to play / 喜欢玩",
          "noise": [
            "plays",
            "are"
          ],
          "accept": [
            "After school we like to play."
          ],
          "id": "47bdbfcd"
        },
        {
          "en": "We like to dance after school.",
          "cn": "我们喜欢放学后跳舞。",
          "hint": "like to dance / 喜欢跳舞",
          "noise": [
            "dancing",
            "is"
          ],
          "accept": [
            "After school we like to dance."
          ],
          "id": "6c50b099"
        },
        {
          "en": "We like to act after school.",
          "cn": "我们喜欢放学后表演。",
          "hint": "we like / 我们喜欢",
          "noise": [
            "likes",
            "acting"
          ],
          "accept": [
            "After school we like to act."
          ],
          "id": "9a7fdc7c"
        },
        {
          "en": "They like to study after school.",
          "cn": "他们喜欢放学后学习。",
          "hint": "they = multiple people / 他们",
          "noise": [
            "them",
            "studies"
          ],
          "accept": [
            "After school they like to study."
          ],
          "id": "d4e88b4b"
        },
        {
          "en": "They like to play after school.",
          "cn": "他们喜欢放学后玩耍。",
          "hint": "they like / 他们喜欢",
          "noise": [
            "playing",
            "are"
          ],
          "accept": [
            "After school they like to play."
          ],
          "id": "cba209a3"
        }
      ]
    },
    {
      "id": "c2",
      "title": "Fun School",
      "icon": "🏫",
      "data": [
        {
          "en": "I like to read after school.",
          "cn": "我喜欢放学后阅读。",
          "hint": "action: read / 动作：阅读",
          "noise": [
            "reads",
            "reading"
          ],
          "accept": [
            "After school I like to read."
          ],
          "id": "4032202a"
        },
        {
          "en": "I like to sing after school.",
          "cn": "我喜欢放学后唱歌。",
          "hint": "action: sing / 动作：唱歌",
          "noise": [
            "sings",
            "am"
          ],
          "accept": [
            "After school I like to sing."
          ],
          "id": "c179d6c7"
        },
        {
          "en": "I like to bike after school.",
          "cn": "我喜欢放学后骑自行车。",
          "hint": "action: bike / 动作：骑车",
          "noise": [
            "bikes",
            "biking"
          ],
          "accept": [
            "After school I like to bike."
          ],
          "id": "941714da"
        },
        {
          "en": "We like to read after school.",
          "cn": "我们喜欢放学后阅读。",
          "hint": "we like to / 我们喜欢...",
          "noise": [
            "reading",
            "us"
          ],
          "accept": [
            "After school we like to read."
          ],
          "id": "7aa7c9e2"
        },
        {
          "en": "We like to sing after school.",
          "cn": "我们喜欢放学后唱歌。",
          "hint": "after school / 放学后",
          "noise": [
            "sings",
            "are"
          ],
          "accept": [
            "After school we like to sing."
          ],
          "id": "7e931cb9"
        },
        {
          "en": "We like to bike after school.",
          "cn": "我们喜欢放学后骑自行车。",
          "hint": "bike = ride a bike / 骑自行车",
          "noise": [
            "biking",
            "rides"
          ],
          "accept": [
            "After school we like to bike."
          ],
          "id": "cc1e2bbd"
        },
        {
          "en": "We like to have fun after school.",
          "cn": "我们喜欢放学后玩得开心。",
          "hint": "have fun / 玩得开心",
          "noise": [
            "has",
            "funs"
          ],
          "accept": [
            "After school we like to have fun."
          ],
          "id": "de1afe91"
        },
        {
          "en": "I like to have fun after school.",
          "cn": "我喜欢放学后玩得开心。",
          "hint": "have fun / 玩得开心",
          "noise": [
            "having",
            "am"
          ],
          "accept": [
            "After school I like to have fun."
          ],
          "id": "5bf36f1f"
        },
        {
          "en": "They like to read after school.",
          "cn": "他们喜欢放学后阅读。",
          "hint": "they = multiple people / 他们",
          "noise": [
            "reads",
            "them"
          ],
          "accept": [
            "After school they like to read."
          ],
          "id": "f6f20c5b"
        },
        {
          "en": "They like to sing after school.",
          "cn": "他们喜欢放学后唱歌。",
          "hint": "they like / 他们喜欢",
          "noise": [
            "singing",
            "is"
          ],
          "accept": [
            "After school they like to sing."
          ],
          "id": "a80d9e58"
        }
      ]
    },
    {
      "id": "c3",
      "title": "Third Person",
      "icon": "👦",
      "data": [
        {
          "en": "He likes to study after school.",
          "cn": "他喜欢放学后学习。",
          "hint": "Add 's' to like for He / 第三人称单数加 's'",
          "noise": [
            "like",
            "studies"
          ],
          "accept": [
            "After school he likes to study."
          ],
          "id": "b794f259"
        },
        {
          "en": "She likes to play after school.",
          "cn": "她喜欢放学后玩耍。",
          "hint": "Add 's' to like for She / 第三人称单数加 's'",
          "noise": [
            "like",
            "playing"
          ],
          "accept": [
            "After school she likes to play."
          ],
          "id": "0abd6278"
        },
        {
          "en": "He likes to dance after school.",
          "cn": "他喜欢放学后跳舞。",
          "hint": "he likes / 他喜欢",
          "noise": [
            "like",
            "dances"
          ],
          "accept": [
            "After school he likes to dance."
          ],
          "id": "8d95bbc6"
        },
        {
          "en": "She likes to act after school.",
          "cn": "她喜欢放学后表演。",
          "hint": "she likes / 她喜欢",
          "noise": [
            "like",
            "acting"
          ],
          "accept": [
            "After school she likes to act."
          ],
          "id": "344dd4fb"
        },
        {
          "en": "He likes to read after school.",
          "cn": "他喜欢放学后阅读。",
          "hint": "action: read / 动作：阅读",
          "noise": [
            "like",
            "reads"
          ],
          "accept": [
            "After school he likes to read."
          ],
          "id": "6eba5912"
        },
        {
          "en": "She likes to sing after school.",
          "cn": "她喜欢放学后唱歌。",
          "hint": "action: sing / 动作：唱歌",
          "noise": [
            "like",
            "sings"
          ],
          "accept": [
            "After school she likes to sing."
          ],
          "id": "01e4e316"
        },
        {
          "en": "He likes to bike after school.",
          "cn": "他喜欢放学后骑自行车。",
          "hint": "action: bike / 动作：骑车",
          "noise": [
            "like",
            "bikes"
          ],
          "accept": [
            "After school he likes to bike."
          ],
          "id": "fc810c1d"
        },
        {
          "en": "She likes to have fun after school.",
          "cn": "她喜欢放学后玩得开心。",
          "hint": "have fun / 玩得开心",
          "noise": [
            "like",
            "has"
          ],
          "accept": [
            "After school she likes to have fun."
          ],
          "id": "f559d176"
        },
        {
          "en": "The boy likes to play.",
          "cn": "这个男孩喜欢玩耍。",
          "hint": "The boy = he / 男孩用第单数形式",
          "noise": [
            "like",
            "playing"
          ],
          "id": "8d3a50bc"
        },
        {
          "en": "The girl likes to read.",
          "cn": "这个女孩喜欢阅读。",
          "hint": "The girl = she / 女孩用单数形式",
          "noise": [
            "like",
            "reads"
          ],
          "id": "51f317b9"
        }
      ]
    },
    {
      "id": "c4",
      "title": "Extra Practice",
      "icon": "⭐",
      "data": [
        {
          "en": "Do you like to study?",
          "cn": "你喜欢学习吗？",
          "hint": "Start with 'Do' / 以 'Do' 开头",
          "noise": [
            "Are",
            "studies"
          ],
          "id": "45caa351"
        },
        {
          "en": "Do you like to play?",
          "cn": "你喜欢玩耍吗？",
          "hint": "Start with 'Do' / 以 'Do' 开头",
          "noise": [
            "Does",
            "playing"
          ],
          "id": "fe063f82"
        },
        {
          "en": "Do you like to dance?",
          "cn": "你喜欢跳舞吗？",
          "hint": "like to dance / 喜欢跳舞",
          "noise": [
            "Are",
            "dances"
          ],
          "id": "1e283b3a"
        },
        {
          "en": "Do you like to act?",
          "cn": "你喜欢表演吗？",
          "hint": "like to act / 喜欢表演",
          "noise": [
            "Is",
            "acting"
          ],
          "id": "0e5746bb"
        },
        {
          "en": "Do you like to read?",
          "cn": "你喜欢阅读吗？",
          "hint": "like to read / 喜欢阅读",
          "noise": [
            "Does",
            "reads"
          ],
          "id": "c6f1ea1a"
        },
        {
          "en": "Do you like to sing?",
          "cn": "你喜欢唱歌吗？",
          "hint": "like to sing / 喜欢唱歌",
          "noise": [
            "Are",
            "sings"
          ],
          "id": "6d29346a"
        },
        {
          "en": "Do you like to bike?",
          "cn": "你喜欢骑自行车吗？",
          "hint": "like to bike / 喜欢骑车",
          "noise": [
            "Does",
            "biking"
          ],
          "id": "73206475"
        },
        {
          "en": "Does he like to play?",
          "cn": "他喜欢玩耍吗？",
          "hint": "Use 'Does' for he / 第三人称单数疑问句用 'Does'",
          "noise": [
            "Do",
            "plays"
          ],
          "id": "791c0bbe"
        },
        {
          "en": "Does she like to read?",
          "cn": "她喜欢阅读吗？",
          "hint": "Use 'Does' for she / 第三人称单数疑问句用 'Does'",
          "noise": [
            "Do",
            "reads"
          ],
          "id": "9d77f41c"
        },
        {
          "en": "What do you do after school?",
          "cn": "你放学后做什么？",
          "hint": "Question word 'What' / 疑问词 'What'",
          "noise": [
            "How",
            "does"
          ],
          "id": "057486d9"
        }
      ]
    },
    {
      "id": "c5",
      "title": "Review All",
      "icon": "🏆",
      "data": [
        {
          "en": "I like to study and play.",
          "cn": "我喜欢学习和玩耍。",
          "hint": "Connect with 'and' / 用 'and' 连接",
          "noise": [
            "likes",
            "studying"
          ],
          "id": "f4c48ec0"
        },
        {
          "en": "We like to sing and dance.",
          "cn": "我们喜欢唱歌跳舞。",
          "hint": "sing and dance / 唱歌跳舞",
          "noise": [
            "sings",
            "dancing"
          ],
          "id": "527794c7"
        },
        {
          "en": "He likes to read books.",
          "cn": "他喜欢读书。",
          "hint": "read books / 读书",
          "noise": [
            "like",
            "reading"
          ],
          "id": "2dca2c71"
        },
        {
          "en": "She likes to ride a bike.",
          "cn": "她喜欢骑自行车。",
          "hint": "ride a bike / 骑自行车",
          "noise": [
            "like",
            "rides"
          ],
          "id": "88c9a9e5"
        },
        {
          "en": "I have fun with my friends.",
          "cn": "我和我的朋友们玩得很开心。",
          "hint": "with my friends / 和我的朋友们",
          "noise": [
            "has",
            "friend"
          ],
          "id": "3015b314"
        },
        {
          "en": "We have fun after school.",
          "cn": "我们放学后玩得很开心。",
          "hint": "have fun / 玩得开心",
          "noise": [
            "has",
            "funs"
          ],
          "accept": [
            "After school we have fun."
          ],
          "id": "dae9a506"
        },
        {
          "en": "What are some ways to have fun?",
          "cn": "有哪些玩得开心的方法？",
          "hint": "from focus question / 核心问题",
          "noise": [
            "is",
            "way"
          ],
          "id": "763a14ca"
        },
        {
          "en": "I like to read in the library.",
          "cn": "我喜欢在图书馆阅读。",
          "hint": "in the library / 在图书馆",
          "noise": [
            "reads",
            "on"
          ],
          "id": "d8cd4cdc"
        },
        {
          "en": "He likes to play football.",
          "cn": "他喜欢踢足球。",
          "hint": "play football / 踢足球",
          "noise": [
            "like",
            "plays"
          ],
          "id": "78edbb71"
        },
        {
          "en": "After school is fun.",
          "cn": "放学后很有趣。",
          "hint": "fun = enjoyable / 很有趣",
          "noise": [
            "are",
            "funs"
          ],
          "id": "7fc1eb69"
        }
      ]
    }
  ]
}