{
  "unit_vocabulary": [
    {
      "word": "healthy",
      "meaning": "有益健康的 (adj.)",
      "page_number": 3,
      "context_sentence": "Apples can be healthy.",
      "ipa": "/ˈhelθi/",
      "comparison": "healthy vs wealthy",
      "syllable_type": "heal-thy",
      "memorization_hook": "heal（治愈）+ thy（你的）-> 能够治愈你身体的食物是有益健康的。"
    },
    {
      "word": "seeds",
      "meaning": "种子 (n.)",
      "page_number": 6,
      "context_sentence": "Seeds can be healthy.",
      "ipa": "/siːdz/",
      "comparison": "seeds vs deeds",
      "syllable_type": "元音字母组合音节 (Vowel Team)",
      "memorization_hook": "see（看见）+ ds -> 看见地上长出了种子的嫩芽。"
    },
    {
      "word": "snacks",
      "meaning": "零食 (n.)",
      "page_number": 10,
      "context_sentence": "Healthy snacks taste good!",
      "ipa": "/snæks/",
      "comparison": "snacks vs snakes",
      "syllable_type": "闭音节 (Closed)",
      "memorization_hook": "s + nack（脖子）+ s -> 伸长脖子张望，看看有什么零食可以吃。"
    },
    {
      "word": "apples",
      "meaning": "苹果 (n.)",
      "page_number": 3,
      "context_sentence": "Apples can be healthy.",
      "ipa": "/ˈæplz/",
      "comparison": "apples vs application",
      "syllable_type": "ap-ples",
      "memorization_hook": "ap（阿婆）+ ple（请）+ s -> 阿婆请大家吃大苹果。"
    },
    {
      "word": "celery",
      "meaning": "芹菜 (n.)",
      "page_number": 4,
      "context_sentence": "Celery can be healthy.",
      "ipa": "/ˈseləri/",
      "comparison": "celery vs salary",
      "syllable_type": "cel-er-y",
      "memorization_hook": "cel（细胞）+ er + y -> 芹菜纤维多，对身体细胞非常好。"
    },
    {
      "word": "nuts",
      "meaning": "坚果 (n.)",
      "page_number": 5,
      "context_sentence": "Nuts can be healthy.",
      "ipa": "/nʌts/",
      "comparison": "nuts vs huts",
      "syllable_type": "闭音节 (Closed)",
      "memorization_hook": "n（牛）+ ut（外面）+ s -> 牛在外面吃坚果。"
    },
    {
      "word": "cheese",
      "meaning": "奶酪 (n.)",
      "page_number": 7,
      "context_sentence": "Cheese can be healthy.",
      "ipa": "/tʃiːz/",
      "comparison": "cheese vs choose",
      "syllable_type": "元音字母组合音节 (Vowel Team)",
      "memorization_hook": "chee（吃）+ se（色）-> 吃黄色亮丽的奶酪。"
    },
    {
      "word": "carrots",
      "meaning": "胡萝卜 (n.)",
      "page_number": 8,
      "context_sentence": "Carrots can be healthy.",
      "ipa": "/ˈkærəts/",
      "comparison": "carrots vs parrots",
      "syllable_type": "car-rots",
      "memorization_hook": "car（汽车）+ rot（腐烂）+ s -> 汽车里装满了胡萝卜，都快要腐烂了。"
    },
    {
      "word": "cereal",
      "meaning": "麦片 (n.)",
      "page_number": 9,
      "context_sentence": "Cereal can be healthy.",
      "ipa": "/ˈsɪəriəl/",
      "comparison": "cereal vs serial",
      "syllable_type": "ce-re-al",
      "memorization_hook": "ce（测）+ re（热）+ al -> 测测麦片粥的热度。"
    },
    {
      "word": "taste",
      "meaning": "尝起来 (v.)",
      "page_number": 10,
      "context_sentence": "Healthy snacks taste good!",
      "ipa": "/teɪst/",
      "comparison": "taste vs paste",
      "syllable_type": "相对开音节 (VCe)",
      "memorization_hook": "ta（他）+ ste（斯特） -> 他去斯特城尝到了美味。"
    },
    {
      "word": "good",
      "meaning": "好的 (adj.)",
      "page_number": 10,
      "context_sentence": "Healthy snacks taste good!",
      "ipa": "/ɡʊd/",
      "comparison": "good vs wood",
      "syllable_type": "元音字母组合音节 (Vowel Team)",
      "memorization_hook": "goo（粘性物）+ d -> 粘在一起的情谊是好的。"
    }
  ],
  "level": "RAZ-B"
}
