{
  "level": "Pupil's Book 1 - Unit 2",
  "title": "Passage Decoder",
  "sections": [
    {
      "title": "Listen. Listen, point and say.",
      "sentences": [
        {
          "id": "pd_d3ajwii8",
          "en": "Look, Matt.",
          "speaker": "Anna",
          "newline": true,
          "highlight": "",
          "options": [
            "听，马特。",
            "找，马特。",
            "看，马特。"
          ],
          "answer": 2
        },
        {
          "id": "pd_lbr77irn",
          "en": "This is our new school.",
          "speaker": "Anna",
          "newline": false,
          "highlight": "",
          "options": [
            "这是我们的旧学校。",
            "那是我们的新学校。",
            "这是我们的新学校。"
          ],
          "answer": 2
        },
        {
          "id": "pd_7nobndz2",
          "en": "This is the playground.",
          "speaker": "Anna",
          "newline": false,
          "highlight": "playground",
          "options": [
            "这是操场。",
            "这是书柜。",
            "这是教室。"
          ],
          "answer": 0
        },
        {
          "id": "pd_ui730hjx",
          "en": "This is your classroom.",
          "speaker": "Anna",
          "newline": false,
          "highlight": "classroom",
          "options": [
            "这是我的教室。",
            "这是你的教室。",
            "这是你的书柜。"
          ],
          "answer": 1
        },
        {
          "id": "pd_5w40pqns",
          "en": "Oh, my classroom's blue.",
          "speaker": "Matt",
          "newline": true,
          "highlight": "classroom",
          "options": [
            "噢，我的教室是蓝色的。",
            "噢，我的教室是红色的。",
            "噢，你的教室是蓝色的。"
          ],
          "answer": 0
        },
        {
          "id": "pd_mgw2nc8n",
          "en": "Who's that woman?",
          "speaker": "Matt",
          "newline": false,
          "highlight": "",
          "options": [
            "那位老师是谁？",
            "那位女士是谁？",
            "那位男士是谁？"
          ],
          "answer": 1
        },
        {
          "id": "pd_xuflup12",
          "en": "She's your teacher.",
          "speaker": "Anna",
          "newline": true,
          "highlight": "teacher",
          "options": [
            "她是你的同学。",
            "她是你的老师。",
            "她是我的老师。"
          ],
          "answer": 1
        },
        {
          "id": "pd_g1gn6dnb",
          "en": "Ooh!",
          "speaker": "Matt",
          "newline": true,
          "highlight": "",
          "options": [
            "嘿！",
            "啊！",
            "噢！"
          ],
          "answer": 2
        },
        {
          "id": "pd_rrj5j87y",
          "en": "My teacher!",
          "speaker": "Matt",
          "newline": false,
          "highlight": "teacher",
          "options": [
            "我的同学！",
            "我的老师！",
            "你的老师！"
          ],
          "answer": 1
        },
        {
          "id": "pd_ywygffb2",
          "en": "Here you are, Matt.",
          "speaker": "Anna",
          "newline": true,
          "highlight": "",
          "options": [
            "给你，马特。",
            "在那，马特。",
            "这是，马特。"
          ],
          "answer": 0
        },
        {
          "id": "pd_itnkv4mz",
          "en": "Here's your bag.",
          "speaker": "Anna",
          "newline": false,
          "highlight": "bag",
          "options": [
            "这是我的书包。",
            "这是你的铅笔。",
            "这是你的书包。"
          ],
          "answer": 2
        },
        {
          "id": "pd_wseehvi8",
          "en": "Your bag's red.",
          "speaker": "Anna",
          "newline": false,
          "highlight": "bag",
          "options": [
            "你的书包是蓝色的。",
            "你的书包是红色的。",
            "我的书包是红色的。"
          ],
          "answer": 1
        },
        {
          "id": "pd_shlyqh7m",
          "en": "And here's your new pencil.",
          "speaker": "Anna",
          "newline": false,
          "highlight": "pencil",
          "options": [
            "那是你的新铅笔。",
            "这是你的新铅笔。",
            "这是你的新书包。"
          ],
          "answer": 1
        },
        {
          "id": "pd_ai6ta7sn",
          "en": "Ooh, a yellow pencil.",
          "speaker": "Matt",
          "newline": true,
          "highlight": "pencil",
          "options": [
            "噢，一支红色的铅笔。",
            "噢，一支黄色的蜡笔。",
            "噢，一支黄色的铅笔。"
          ],
          "answer": 2
        },
        {
          "id": "pd_lo1ljzgu",
          "en": "Yellow's my favourite colour.",
          "speaker": "Matt",
          "newline": false,
          "highlight": "favourite colour",
          "options": [
            "黄色是你的最喜欢的颜色。",
            "红色是我最喜欢的颜色。",
            "黄色是我最喜欢的颜色。"
          ],
          "answer": 2
        },
        {
          "id": "pd_b1mxr79m",
          "en": "Look, Anna!",
          "speaker": "Matt",
          "newline": false,
          "highlight": "",
          "options": [
            "看，安娜！",
            "听，安娜！",
            "走，安娜！"
          ],
          "answer": 0
        },
        {
          "id": "pd_y7iolrep",
          "en": "Jim and Jenny!",
          "speaker": "Matt",
          "newline": false,
          "highlight": "",
          "options": [
            "吉姆和马特！",
            "吉姆和珍妮！",
            "吉姆和安娜！"
          ],
          "answer": 1
        },
        {
          "id": "pd_0rpsqgih",
          "en": "Yes, our new friends.",
          "speaker": "Anna",
          "newline": true,
          "highlight": "",
          "options": [
            "是的，我们的新朋友。",
            "是的，我们的老朋友。",
            "是的，我们的新老师。"
          ],
          "answer": 0
        },
        {
          "id": "pd_4wkg7y1j",
          "en": "Hi, Jim!",
          "speaker": "Matt",
          "newline": true,
          "highlight": "",
          "options": [
            "再见，吉姆！",
            "嗨，吉姆！",
            "你好，珍妮！"
          ],
          "answer": 1
        },
        {
          "id": "pd_kuos2ie4",
          "en": "Hi, Jenny!",
          "speaker": "Matt",
          "newline": false,
          "highlight": "",
          "options": [
            "嗨，珍妮！",
            "嗨，吉姆！",
            "嗨，安娜！"
          ],
          "answer": 0
        },
        {
          "id": "pd_puq6lqgf",
          "en": "Hi, Matt!",
          "speaker": "Jim and Jenny",
          "newline": true,
          "highlight": "",
          "options": [
            "嗨，马特！",
            "嗨，吉姆！",
            "嗨，珍妮！"
          ],
          "answer": 0
        },
        {
          "id": "pd_w54cnjfs",
          "en": "Hi, Anna!",
          "speaker": "Jim and Jenny",
          "newline": false,
          "highlight": "",
          "options": [
            "嗨，马特！",
            "嗨，安娜！",
            "嗨，吉姆！"
          ],
          "answer": 1
        }
      ]
    },
    {
      "title": "Listen. Who says it? Matt or Jim? Listen again and draw lines.",
      "sentences": [
        {
          "id": "pd_n328x25v",
          "en": "OK, Matt.",
          "speaker": "Jenny",
          "newline": true,
          "highlight": "",
          "options": [
            "好的，吉姆。",
            "好的，安娜。",
            "好的，马特。"
          ],
          "answer": 2
        },
        {
          "id": "pd_dmtoknsy",
          "en": "It's your turn.",
          "speaker": "Jenny",
          "newline": false,
          "highlight": "",
          "options": [
            "轮到我了。",
            "轮到你了。",
            "轮到他了。"
          ],
          "answer": 1
        },
        {
          "id": "pd_ur1edwu8",
          "en": "What are they?",
          "speaker": "Jenny",
          "newline": false,
          "highlight": "",
          "options": [
            "它们是什么？",
            "它们是谁？",
            "它们在哪里？"
          ],
          "answer": 0
        },
        {
          "id": "pd_fglrg9pt",
          "en": "Are they birds?",
          "speaker": "Jenny",
          "newline": false,
          "highlight": "",
          "options": [
            "它们是鸟吗？",
            "它们是猫吗？",
            "它们是狗吗？"
          ],
          "answer": 0
        },
        {
          "id": "pd_47tf2go7",
          "en": "Birds?",
          "speaker": "Matt",
          "newline": true,
          "highlight": "",
          "options": [
            "狗？",
            "鸟？",
            "猫？"
          ],
          "answer": 1
        },
        {
          "id": "pd_xwfw5n5m",
          "en": "No ...",
          "speaker": "Matt",
          "newline": false,
          "highlight": "",
          "options": [
            "不……",
            "好吧……",
            "是的……"
          ],
          "answer": 0
        },
        {
          "id": "pd_gqz7cvos",
          "en": "er, no...",
          "speaker": "Matt",
          "newline": false,
          "highlight": "",
          "options": [
            "呃，是的……",
            "呃，好吧……",
            "呃，不……"
          ],
          "answer": 2
        },
        {
          "id": "pd_t4avza36",
          "en": "Now it's your turn, Jim.",
          "speaker": "Matt",
          "newline": false,
          "highlight": "",
          "options": [
            "现在轮到你了，吉姆。",
            "现在轮到你了，安娜。",
            "现在轮到你了，马特。"
          ],
          "answer": 0
        },
        {
          "id": "pd_agmdycdj",
          "en": "Are they buses?",
          "speaker": "Matt",
          "newline": false,
          "highlight": "",
          "options": [
            "它们是自行车吗？",
            "它们是公共汽车吗？",
            "它们是小汽车吗？"
          ],
          "answer": 1
        },
        {
          "id": "pd_i85a5lpo",
          "en": "Er, no.",
          "speaker": "Jenny",
          "newline": true,
          "highlight": "",
          "options": [
            "呃，不是。",
            "呃，是的。",
            "呃，也许。"
          ],
          "answer": 0
        },
        {
          "id": "pd_h92qco5g",
          "en": "They're school things.",
          "speaker": "Jenny",
          "newline": false,
          "highlight": "",
          "options": [
            "它们是教室用品。",
            "它们是文具盒用品。",
            "它们是学校用品。"
          ],
          "answer": 2
        },
        {
          "id": "pd_uhr7kcnc",
          "en": "Matt and Jim: Ah!",
          "speaker": "Jim",
          "newline": true,
          "highlight": "",
          "options": [
            "马特和吉姆：啊！",
            "马特和吉姆：噢！",
            "马特和吉姆：嘿！"
          ],
          "answer": 0
        },
        {
          "id": "pd_qingibkc",
          "en": "OK.",
          "speaker": "Jenny",
          "newline": true,
          "highlight": "",
          "options": [
            "好的。",
            "没问题。",
            "再见。"
          ],
          "answer": 0
        },
        {
          "id": "pd_smjgryzx",
          "en": "Are they crayons?",
          "speaker": "Jenny",
          "newline": false,
          "highlight": "crayons",
          "options": [
            "它们是书本吗？",
            "它们是铅笔吗？",
            "它们是蜡笔吗？"
          ],
          "answer": 2
        },
        {
          "id": "pd_tdzzzg1k",
          "en": "Yes, they are.",
          "speaker": "Matt",
          "newline": true,
          "highlight": "",
          "options": [
            "是的，它是。",
            "是的，我们是。",
            "是的，它们是。"
          ],
          "answer": 2
        },
        {
          "id": "pd_seueuzny",
          "en": "They're crayons.",
          "speaker": "Matt",
          "newline": false,
          "highlight": "crayons",
          "options": [
            "它们是蜡笔。",
            "它们是书包。",
            "它们是铅笔。"
          ],
          "answer": 0
        },
        {
          "id": "pd_viqyjijx",
          "en": "Well done, Matt!",
          "speaker": "Matt",
          "newline": false,
          "highlight": "",
          "options": [
            "做得好，吉姆！",
            "干得好，马特！",
            "做得好，老师！"
          ],
          "answer": 1
        },
        {
          "id": "pd_g9bqxl3r",
          "en": "Now it's your turn, Jim.",
          "speaker": "Jenny",
          "newline": true,
          "highlight": "",
          "options": [
            "现在轮到你了，吉姆。",
            "现在轮到你了，马特。",
            "现在轮到我了，吉姆。"
          ],
          "answer": 0
        },
        {
          "id": "pd_2k0ef9qx",
          "en": "What are they?",
          "speaker": "Jenny",
          "newline": false,
          "highlight": "",
          "options": [
            "它们是什么？",
            "它们在哪里？",
            "它们是谁？"
          ],
          "answer": 0
        },
        {
          "id": "pd_tvvk0h0f",
          "en": "Are they books?",
          "speaker": "Anna",
          "newline": true,
          "highlight": "",
          "options": [
            "它们是椅子吗？",
            "它们是桌子吗？",
            "它们是书吗？"
          ],
          "answer": 2
        },
        {
          "id": "pd_fvas695n",
          "en": "Anna: No.",
          "speaker": "Jim",
          "newline": true,
          "highlight": "",
          "options": [
            "安娜：可能。",
            "安娜：是的。",
            "安娜：不是。"
          ],
          "answer": 2
        },
        {
          "id": "pd_jah2bhuq",
          "en": "Are they bags?",
          "speaker": "Matt",
          "newline": true,
          "highlight": "bag",
          "options": [
            "它们是书包吗？",
            "它们是铅笔吗？",
            "它们是橱柜吗？"
          ],
          "answer": 0
        },
        {
          "id": "pd_7w4uqa34",
          "en": "No.",
          "speaker": "Anna",
          "newline": true,
          "highlight": "",
          "options": [
            "不是。",
            "也许。",
            "是的。"
          ],
          "answer": 0
        },
        {
          "id": "pd_o8siayeg",
          "en": "Are they pencils?",
          "speaker": "Jim",
          "newline": true,
          "highlight": "pencil",
          "options": [
            "它们是铅笔吗？",
            "它们是蜡笔吗？",
            "那是铅笔吗？"
          ],
          "answer": 0
        },
        {
          "id": "pd_1ceboqvc",
          "en": "Yes!",
          "speaker": "Anna",
          "newline": true,
          "highlight": "",
          "options": [
            "是的！",
            "不是！",
            "太好了！"
          ],
          "answer": 0
        },
        {
          "id": "pd_t6frgstl",
          "en": "They're pencils.",
          "speaker": "Anna",
          "newline": false,
          "highlight": "pencil",
          "options": [
            "它们在铅笔盒里。",
            "它们是铅笔。",
            "它们是蜡笔。"
          ],
          "answer": 1
        },
        {
          "id": "pd_nwg7udcb",
          "en": "Well done, Jim!",
          "speaker": "Anna",
          "newline": false,
          "highlight": "",
          "options": [
            "干得好，吉姆！",
            "你是吉姆吗？",
            "做得不好，吉姆！"
          ],
          "answer": 0
        }
      ]
    },
    {
      "title": "Listen. Listen again and do the actions.",
      "sentences": [
        {
          "id": "pd_fx5sjqc8",
          "en": "Dad, where's my green pencil?",
          "speaker": "Sue",
          "newline": true,
          "highlight": "pencil",
          "options": [
            "爸爸，我的绿色蜡笔在哪里？",
            "爸爸，我的绿色铅笔在哪里？",
            "爸爸，我的绿色铅笔在桌子上吗？"
          ],
          "answer": 1
        },
        {
          "id": "pd_2gu63hao",
          "en": "Is it on the table, Sue?",
          "speaker": "Dad",
          "newline": true,
          "highlight": "table, on",
          "options": [
            "它在椅子上吗，苏？",
            "它在桌子下面吗，苏？",
            "它在桌子上吗，苏？"
          ],
          "answer": 2
        },
        {
          "id": "pd_d4xqr5ds",
          "en": "No, it isn't.",
          "speaker": "Sue",
          "newline": true,
          "highlight": "",
          "options": [
            "它在桌子上。",
            "是的，它在。",
            "不，它不在。"
          ],
          "answer": 2
        },
        {
          "id": "pd_b0926he6",
          "en": "That's my green crayon.",
          "speaker": "Sue",
          "newline": false,
          "highlight": "crayons",
          "options": [
            "这是我的绿色蜡笔。",
            "那是我的绿色铅笔。",
            "那是我的绿色蜡笔。"
          ],
          "answer": 2
        },
        {
          "id": "pd_yecp8ac0",
          "en": "Is it under the chair?",
          "speaker": "Dad",
          "newline": true,
          "highlight": "under, chairs",
          "options": [
            "它在桌子下面吗？",
            "它在椅子下面吗？",
            "它在椅子上面吗？"
          ],
          "answer": 1
        },
        {
          "id": "pd_goxzcpjk",
          "en": "No, it isn't under the chair.",
          "speaker": "Sue",
          "newline": true,
          "highlight": "under, chairs",
          "options": [
            "不，它不在椅子下面。",
            "不，它不在桌子下面。",
            "是的，它在椅子下面。"
          ],
          "answer": 0
        },
        {
          "id": "pd_981dmmcb",
          "en": "Oh, where is it?",
          "speaker": "Sue",
          "newline": false,
          "highlight": "",
          "options": [
            "噢，它是什么？",
            "噢，它在哪里？",
            "噢，它在桌子上吗？"
          ],
          "answer": 1
        },
        {
          "id": "pd_y6iqjgyx",
          "en": "Is it on the bookcase?",
          "speaker": "Dad",
          "newline": true,
          "highlight": "bookcase, on",
          "options": [
            "它在桌子上吗？",
            "它在书柜里吗？",
            "它在书柜上吗？"
          ],
          "answer": 2
        },
        {
          "id": "pd_zih8yprs",
          "en": "Is it under that purple book?",
          "speaker": "Dad",
          "newline": false,
          "highlight": "under",
          "options": [
            "它在那本紫色书下面吗？",
            "它在那本紫色书上面吗？",
            "它在那个书柜下面吗？"
          ],
          "answer": 0
        },
        {
          "id": "pd_6vrqwnmh",
          "en": "No, it isn't.",
          "speaker": "Sue",
          "newline": true,
          "highlight": "",
          "options": [
            "是的，它在。",
            "它在书下面。",
            "不，它不在。"
          ],
          "answer": 2
        },
        {
          "id": "pd_cwrarfql",
          "en": "That's my blue pencil.",
          "speaker": "Sue",
          "newline": false,
          "highlight": "pencil",
          "options": [
            "那是我的蓝色铅笔。",
            "那是我的蓝色蜡笔。",
            "这是我的蓝色铅笔。"
          ],
          "answer": 0
        },
        {
          "id": "pd_b5rrmd01",
          "en": "Oh, where is it?",
          "speaker": "Sue",
          "newline": false,
          "highlight": "",
          "options": [
            "哦，他在哪里？",
            "哦，那是什么？",
            "哦，它在哪里？"
          ],
          "answer": 2
        },
        {
          "id": "pd_f9klurbz",
          "en": "Sue.",
          "speaker": "Dad",
          "newline": true,
          "highlight": "",
          "options": [
            "苏。",
            "书。",
            "树。"
          ],
          "answer": 0
        },
        {
          "id": "pd_o5geohqa",
          "en": "Look at your bag ...",
          "speaker": "Dad",
          "newline": false,
          "highlight": "bag",
          "options": [
            "看看你的铅笔……",
            "看看你的桌子……",
            "看看你的书包……"
          ],
          "answer": 2
        },
        {
          "id": "pd_a4aowt22",
          "en": "on the chair.",
          "speaker": "Dad",
          "newline": false,
          "highlight": "on, chairs",
          "options": [
            "在椅子上。",
            "在桌子上。",
            "在椅子下。"
          ],
          "answer": 0
        },
        {
          "id": "pd_59lrpqho",
          "en": "Yes ...?",
          "speaker": "Sue",
          "newline": true,
          "highlight": "",
          "options": [
            "是的……？",
            "好的……？",
            "在哪……？"
          ],
          "answer": 0
        },
        {
          "id": "pd_451ch8m7",
          "en": "Your green pencil's in your bag, Sue.",
          "speaker": "Dad",
          "newline": true,
          "highlight": "pencil, in, bag",
          "options": [
            "苏，你的绿色铅笔在你的桌子上。",
            "苏，你的绿色蜡笔在你的书包里。",
            "苏，你的绿色铅笔在你的书包里。"
          ],
          "answer": 2
        },
        {
          "id": "pd_t735bd8b",
          "en": "Oh, yes.",
          "speaker": "Sue",
          "newline": true,
          "highlight": "",
          "options": [
            "哦，是的。",
            "哦，不是。",
            "哦，好的。"
          ],
          "answer": 0
        },
        {
          "id": "pd_9b3ai23n",
          "en": "It is.",
          "speaker": "Sue",
          "newline": false,
          "highlight": "in",
          "options": [
            "它在里面。",
            "它在下面。",
            "它在上面。"
          ],
          "answer": 0
        },
        {
          "id": "pd_ppxm8i4z",
          "en": "Thanks, Dad.",
          "speaker": "Sue",
          "newline": false,
          "highlight": "",
          "options": [
            "谢谢，老师。",
            "谢谢，爸爸。",
            "谢谢，同学。"
          ],
          "answer": 1
        },
        {
          "id": "pd_t9d667e2",
          "en": "Now, Sue.",
          "speaker": "Dad",
          "newline": true,
          "highlight": "",
          "options": [
            "再见，苏。",
            "现在，苏。",
            "过来，苏。"
          ],
          "answer": 1
        },
        {
          "id": "pd_7kijdvsy",
          "en": "It's time for school.",
          "speaker": "Dad",
          "newline": false,
          "highlight": "",
          "options": [
            "休息时间到了。",
            "放学时间到了。",
            "上学时间到了。"
          ],
          "answer": 2
        }
      ]
    },
    {
      "title": "Look. Find and tick . / The bird and the cat",
      "sentences": [
        {
          "id": "pd_ow3zpm2l",
          "en": "Shh, children!",
          "speaker": "Teacher",
          "newline": true,
          "highlight": "",
          "options": [
            "嘘，孩子们！",
            "嘘，爸爸！",
            "嘘，老师！"
          ],
          "answer": 0
        },
        {
          "id": "pd_4buuh5vw",
          "en": "Please copy.",
          "speaker": "Teacher",
          "newline": false,
          "highlight": "",
          "options": [
            "请画画。",
            "请阅读。",
            "请抄写。"
          ],
          "answer": 2
        },
        {
          "id": "pd_h83lgrwx",
          "en": "Draw and write.",
          "speaker": "Teacher",
          "newline": false,
          "highlight": "",
          "options": [
            "画画并阅读。",
            "画画并写字。",
            "写字并阅读。"
          ],
          "answer": 1
        },
        {
          "id": "pd_me6nxou8",
          "en": "Look, Tom.",
          "speaker": "Annie",
          "newline": true,
          "highlight": "",
          "options": [
            "看，汤姆。",
            "看，老师。",
            "看，苏。"
          ],
          "answer": 0
        },
        {
          "id": "pd_qhcdafa0",
          "en": "It's a yellow bird.",
          "speaker": "Annie",
          "newline": false,
          "highlight": "",
          "options": [
            "那是一只黄色的猫。",
            "那是一只黄色的狗。",
            "那是一只黄色的鸟。"
          ],
          "answer": 2
        },
        {
          "id": "pd_6ylrg8j1",
          "en": "Oh, yes!",
          "speaker": "Tom",
          "newline": true,
          "highlight": "",
          "options": [
            "噢，好的！",
            "噢，是的！",
            "噢，不是！"
          ],
          "answer": 1
        },
        {
          "id": "pd_ogj6x13d",
          "en": "It's in the window!",
          "speaker": "Tom",
          "newline": false,
          "highlight": "in",
          "options": [
            "它在窗户里！",
            "它在窗户下！",
            "它在窗户上！"
          ],
          "answer": 0
        },
        {
          "id": "pd_8edeus2o",
          "en": "Look, Annie.",
          "speaker": "Tom",
          "newline": false,
          "highlight": "",
          "options": [
            "找，安妮。",
            "看，安妮。",
            "听，安妮。"
          ],
          "answer": 1
        },
        {
          "id": "pd_l3k8dd8k",
          "en": "It's Hugo, the school cat!",
          "speaker": "Tom",
          "newline": false,
          "highlight": "",
          "options": [
            "那是雨果，学校的猫！",
            "那是雨果，学校的鸟！",
            "那是雨果，学校的老师！"
          ],
          "answer": 0
        },
        {
          "id": "pd_xs6sew4z",
          "en": "Oh, yes!",
          "speaker": "Annie",
          "newline": true,
          "highlight": "",
          "options": [
            "噢，好吧！",
            "噢，真的吗？",
            "噢，是的！"
          ],
          "answer": 2
        },
        {
          "id": "pd_npuiq0b6",
          "en": "Hello, Hugo.",
          "speaker": "Annie",
          "newline": false,
          "highlight": "",
          "options": [
            "你好，雨果。",
            "谢谢，雨果。",
            "再见，雨果。"
          ],
          "answer": 0
        },
        {
          "id": "pd_ciurkp7p",
          "en": "Where's the bird?",
          "speaker": "Annie",
          "newline": false,
          "highlight": "",
          "options": [
            "鸟在哪里？",
            "猫在哪里？",
            "老师在哪里？"
          ],
          "answer": 0
        },
        {
          "id": "pd_vg2374uz",
          "en": "It's on the teacher's bag.",
          "speaker": "Tom",
          "newline": true,
          "highlight": "on, teacher, bag",
          "options": [
            "它在老师的椅子下。",
            "它在老师的桌子上。",
            "它在老师的包上。"
          ],
          "answer": 2
        },
        {
          "id": "pd_2lanpdfw",
          "en": "Look at Hugo.",
          "speaker": "Tom",
          "newline": false,
          "highlight": "",
          "options": [
            "画雨果。",
            "看雨果。",
            "找雨果。"
          ],
          "answer": 1
        },
        {
          "id": "pd_aesysika",
          "en": "Oh, no!",
          "speaker": "Tom",
          "newline": false,
          "highlight": "",
          "options": [
            "噢，天哪！",
            "噢，好吧！",
            "噢，不！"
          ],
          "answer": 2
        },
        {
          "id": "pd_h8cyh7mw",
          "en": "Now the bag's on the floor.",
          "speaker": "Annie",
          "newline": true,
          "highlight": "bag, on",
          "options": [
            "现在包在地板上。",
            "现在包在椅子下。",
            "现在包在桌子上。"
          ],
          "answer": 0
        },
        {
          "id": "pd_76voaan7",
          "en": "And the bird's on the crayon box.",
          "speaker": "Annie",
          "newline": false,
          "highlight": "on, crayons",
          "options": [
            "鸟在蜡笔盒里。",
            "鸟在蜡笔盒下。",
            "鸟在蜡笔盒上。"
          ],
          "answer": 2
        },
        {
          "id": "pd_he2y8zup",
          "en": "Oh, no!",
          "speaker": "Tom",
          "newline": true,
          "highlight": "",
          "options": [
            "噢，是的！",
            "噢，不！",
            "噢，真的吗？"
          ],
          "answer": 1
        },
        {
          "id": "pd_qjjamm5f",
          "en": "Oops!",
          "speaker": "Tom",
          "newline": false,
          "highlight": "",
          "options": [
            "哎呀！",
            "再见！",
            "你好！"
          ],
          "answer": 0
        },
        {
          "id": "pd_kmqke2ga",
          "en": "Now the crayons are on the floor.",
          "speaker": "Tom",
          "newline": false,
          "highlight": "crayons, on",
          "options": [
            "现在蜡笔在地板上。",
            "现在蜡笔在柜子里。",
            "现在蜡笔在桌子上。"
          ],
          "answer": 0
        },
        {
          "id": "pd_1ld8l5l1",
          "en": "And the bird's on the cupboard.",
          "speaker": "Tom",
          "newline": false,
          "highlight": "cupboards, on",
          "options": [
            "还有那只鸟在柜子下。",
            "还有那只猫在柜子上。",
            "还有那只鸟在柜子上。"
          ],
          "answer": 2
        },
        {
          "id": "pd_52imxvoh",
          "en": "Oh, no!",
          "speaker": "Annie",
          "newline": true,
          "highlight": "",
          "options": [
            "噢，好！",
            "噢，是的！",
            "噢，不！"
          ],
          "answer": 2
        },
        {
          "id": "pd_dr6w535s",
          "en": "Hugo's on the cupboard too.",
          "speaker": "Annie",
          "newline": false,
          "highlight": "cupboards, on",
          "options": [
            "雨果也在柜子上。",
            "雨果也在桌子上。",
            "雨果也在柜子下。"
          ],
          "answer": 0
        },
        {
          "id": "pd_zrv5m6kb",
          "en": "Where's the bird now?",
          "speaker": "Annie",
          "newline": false,
          "highlight": "",
          "options": [
            "那只猫现在在哪里？",
            "那只鸟刚才在哪里？",
            "那只鸟现在在哪里？"
          ],
          "answer": 2
        },
        {
          "id": "pd_6udoqp39",
          "en": "It's in the window again.",
          "speaker": "Tom",
          "newline": true,
          "highlight": "in",
          "options": [
            "它又在窗户里了。",
            "它又在窗户上了。",
            "它又在窗户下了。"
          ],
          "answer": 0
        },
        {
          "id": "pd_1auredd6",
          "en": "Look!",
          "speaker": "Tom",
          "newline": false,
          "highlight": "",
          "options": [
            "看！",
            "走！",
            "听！"
          ],
          "answer": 0
        },
        {
          "id": "pd_8zxysg3u",
          "en": "OK...",
          "speaker": "Teacher",
          "newline": true,
          "highlight": "",
          "options": [
            "不……",
            "再见……",
            "好的……"
          ],
          "answer": 2
        },
        {
          "id": "pd_oeqirbfq",
          "en": "Oh, no!",
          "speaker": "Teacher",
          "newline": false,
          "highlight": "",
          "options": [
            "噢，好吧！",
            "噢，天哪！",
            "噢，不！"
          ],
          "answer": 2
        },
        {
          "id": "pd_6fsixdgu",
          "en": "My bag, the crayons, the toys!",
          "speaker": "Teacher",
          "newline": false,
          "highlight": "bag, crayons",
          "options": [
            "我的书包，蜡笔，还有玩具！",
            "我的桌子，蜡笔，还有玩具！",
            "我的书包，铅笔，还有玩具！"
          ],
          "answer": 0
        },
        {
          "id": "pd_6cyeonf5",
          "en": "Hugo, you bad cat!",
          "speaker": "Teacher",
          "newline": false,
          "highlight": "",
          "options": [
            "雨果，你这只坏狗！",
            "雨果，你这只坏鸟！",
            "雨果，你这只坏猫！"
          ],
          "answer": 2
        },
        {
          "id": "pd_dmsefpab",
          "en": "I'm angry!",
          "speaker": "Teacher",
          "newline": false,
          "highlight": "",
          "options": [
            "我很开心！",
            "我很生气！",
            "我很累！"
          ],
          "answer": 1
        }
      ]
    },
    {
      "title": "Listen and point. Listen again and stick.",
      "sentences": [
        {
          "id": "pd_dux6i6cr",
          "en": "Look, Bill!",
          "speaker": "Girl",
          "newline": true,
          "highlight": "",
          "options": [
            "看，比尔！",
            "跑，比尔！",
            "听，比尔！"
          ],
          "answer": 0
        },
        {
          "id": "pd_5nil9po8",
          "en": "This is my classroom.",
          "speaker": "Girl",
          "newline": false,
          "highlight": "classroom",
          "options": [
            "这是我的教室。",
            "这是我的书包。",
            "这是我的桌子。"
          ],
          "answer": 0
        },
        {
          "id": "pd_s19r5st0",
          "en": "Oh, it's nice.",
          "speaker": "Boy",
          "newline": true,
          "highlight": "",
          "options": [
            "噢，它很好。",
            "噢，它很大。",
            "噢，它很旧。"
          ],
          "answer": 0
        },
        {
          "id": "pd_ul3769jk",
          "en": "Is that your bag on the red chair?",
          "speaker": "Boy",
          "newline": false,
          "highlight": "bag, on, chairs",
          "options": [
            "那是你在红色桌子上的包吗？",
            "那是你在红色椅子下的包吗？",
            "那是你在红色椅子上的包吗？"
          ],
          "answer": 2
        },
        {
          "id": "pd_l28riw3n",
          "en": "No, my bag's purple.",
          "speaker": "Girl",
          "newline": true,
          "highlight": "bag",
          "options": [
            "不，我的包是紫色的。",
            "不，我的包是黄色的。",
            "不，我的书是紫色的。"
          ],
          "answer": 0
        },
        {
          "id": "pd_05g0v4vm",
          "en": "It's on the yellow chair.",
          "speaker": "Girl",
          "newline": false,
          "highlight": "on, chairs",
          "options": [
            "它在黄色椅子上。",
            "它在黄色桌子上。",
            "它在黄色椅子下。"
          ],
          "answer": 0
        },
        {
          "id": "pd_owtch5dq",
          "en": "Oh, where's your pencil?",
          "speaker": "Boy",
          "newline": true,
          "highlight": "pencil",
          "options": [
            "哦，你的铅笔在什么地方？",
            "哦，你的书在哪里？",
            "哦，你的铅笔在哪里？"
          ],
          "answer": 2
        },
        {
          "id": "pd_s5t5tn7z",
          "en": "It's in the cupboard.",
          "speaker": "Girl",
          "newline": true,
          "highlight": "in, cupboards",
          "options": [
            "它在橱柜上。",
            "它在桌子里。",
            "它在橱柜里。"
          ],
          "answer": 2
        },
        {
          "id": "pd_8buk4k1p",
          "en": "Oh, yes.",
          "speaker": "Boy",
          "newline": true,
          "highlight": "",
          "options": [
            "哦，好的。",
            "哦，不是。",
            "哦，是的。"
          ],
          "answer": 2
        },
        {
          "id": "pd_x9nza2e8",
          "en": "What are they?",
          "speaker": "Boy",
          "newline": false,
          "highlight": "",
          "options": [
            "它们是什么？",
            "它是什么？",
            "它们在哪里？"
          ],
          "answer": 0
        },
        {
          "id": "pd_4jmr4oqj",
          "en": "Where?",
          "speaker": "Girl",
          "newline": true,
          "highlight": "",
          "options": [
            "在哪里？",
            "在什么地方？",
            "是什么？"
          ],
          "answer": 0
        },
        {
          "id": "pd_qgdhgk1d",
          "en": "There, under the table.",
          "speaker": "Boy",
          "newline": true,
          "highlight": "under, table",
          "options": [
            "在那里，在桌子上面。",
            "在那里，在椅子下面。",
            "在那里，在桌子下面。"
          ],
          "answer": 2
        },
        {
          "id": "pd_mr773fel",
          "en": "What are they?",
          "speaker": "Boy",
          "newline": false,
          "highlight": "",
          "options": [
            "它们在哪里？",
            "它是什么？",
            "它们是什么？"
          ],
          "answer": 2
        },
        {
          "id": "pd_8cin5r9k",
          "en": "Oh, yes, they're my crayons.",
          "speaker": "Girl",
          "newline": true,
          "highlight": "crayons",
          "options": [
            "哦，是的，它们是我的书。",
            "哦，是的，它们是我的蜡笔。",
            "哦，是的，它们是我的铅笔。"
          ],
          "answer": 1
        },
        {
          "id": "pd_s7dmd74b",
          "en": "Thank you.",
          "speaker": "Girl",
          "newline": false,
          "highlight": "",
          "options": [
            "再见。",
            "谢谢你。",
            "不客气。"
          ],
          "answer": 1
        },
        {
          "id": "pd_s3xemjoo",
          "en": "Look on the bookcase.",
          "speaker": "Boy",
          "newline": true,
          "highlight": "on, bookcase",
          "options": [
            "看桌子上面。",
            "看书柜上面。",
            "看书柜里面。"
          ],
          "answer": 1
        },
        {
          "id": "pd_o77bilvq",
          "en": "What are they?",
          "speaker": "Boy",
          "newline": false,
          "highlight": "",
          "options": [
            "它们在哪里？",
            "它们是什么？",
            "它是什么？"
          ],
          "answer": 1
        },
        {
          "id": "pd_lwds3qqh",
          "en": "They're the class pets.",
          "speaker": "Girl",
          "newline": true,
          "highlight": "classroom",
          "options": [
            "它们是班级宠物。",
            "它们是班级老师。",
            "它们是班级书本。"
          ],
          "answer": 0
        },
        {
          "id": "pd_ncj42qs6",
          "en": "They're our fish.",
          "speaker": "Girl",
          "newline": false,
          "highlight": "",
          "options": [
            "它们是我们的猫。",
            "它们是我们的鱼。",
            "它们是你们的鱼。"
          ],
          "answer": 1
        },
        {
          "id": "pd_vf3wbfmo",
          "en": "And a pet bird too.",
          "speaker": "Boy",
          "newline": true,
          "highlight": "",
          "options": [
            "还有一只宠物狗。",
            "还有一只宠物鸟。",
            "还有一只宠物猫。"
          ],
          "answer": 1
        },
        {
          "id": "pd_7vix0zi9",
          "en": "A bird?",
          "speaker": "Girl",
          "newline": true,
          "highlight": "",
          "options": [
            "一只猫？",
            "一只鸟？",
            "一只狗？"
          ],
          "answer": 1
        },
        {
          "id": "pd_yng4gw2r",
          "en": "In my classroom?",
          "speaker": "Girl",
          "newline": false,
          "highlight": "in, classroom",
          "options": [
            "在我的书包里吗？",
            "在我的教室里吗？",
            "在我的操场上吗？"
          ],
          "answer": 1
        },
        {
          "id": "pd_4ze185wu",
          "en": "Where?",
          "speaker": "Girl",
          "newline": false,
          "highlight": "",
          "options": [
            "谁在那儿？",
            "是什么？",
            "在哪里？"
          ],
          "answer": 2
        },
        {
          "id": "pd_mvry3382",
          "en": "Look.",
          "speaker": "Girl",
          "newline": false,
          "highlight": "",
          "options": [
            "走。",
            "听。",
            "看。"
          ],
          "answer": 2
        },
        {
          "id": "pd_mojzovov",
          "en": "It's on the board.",
          "speaker": "Girl",
          "newline": false,
          "highlight": "on, board",
          "options": [
            "它在桌子上。",
            "它在黑板上。",
            "它在书柜里。"
          ],
          "answer": 1
        },
        {
          "id": "pd_8o6q7ds1",
          "en": "Yes, it is!",
          "speaker": "Girl",
          "newline": false,
          "highlight": "",
          "options": [
            "不，它不是。",
            "是的，它在那儿。",
            "是的，它是！"
          ],
          "answer": 2
        },
        {
          "id": "pd_11fr1m30",
          "en": "Look.",
          "speaker": "Boy",
          "newline": true,
          "highlight": "",
          "options": [
            "走。",
            "听。",
            "看。"
          ],
          "answer": 2
        },
        {
          "id": "pd_jfw0jpko",
          "en": "It's on the board.",
          "speaker": "Boy",
          "newline": false,
          "highlight": "on, board",
          "options": [
            "它在黑板上。",
            "它在椅子下。",
            "它在书包里。"
          ],
          "answer": 0
        },
        {
          "id": "pd_cd9hepm6",
          "en": "Yes, it is!",
          "speaker": "Boy",
          "newline": false,
          "highlight": "",
          "options": [
            "是的，它是！",
            "是的，它在那儿。",
            "不，它不是。"
          ],
          "answer": 0
        }
      ]
    }
  ]
}