{
  "title": "Yummy food",
  "level": "Grade 3 Semester 2 - Unit 3",
  "primaryColor": "#10b981",
  "primaryColorDark": "#059669",
  "storageSuffix": "_g3s2_u3",
  "passcode": "IADBA",
  "ipaDict": {
    "apples": "ˈæplz",
    "oranges": "ˈɒrɪndʒɪz",
    "strawberries": "ˈstrɔːbəriz",
    "tomatoes": "təˈmɑːtəʊz",
    "noodles": "ˈnuːdlz",
    "carrots": "ˈkærəts",
    "chicken": "ˈtʃɪkɪn",
    "fish": "fɪʃ",
    "rice": "raɪs",
    "salad": "ˈsæləd",
    "bananas": "bəˈnɑːnəz",
    "beans": "biːnz",
    "cucumbers": "ˈkjuːkʌmbəz",
    "grapes": "ɡreɪps",
    "breakfast": "ˈbrekfəst",
    "early": "ˈɜːli",
    "dumplings": "ˈdʌmplɪŋz",
    "sushi": "ˈsuːʃi",
    "hot dogs": "hɒt dɒɡz"
  },
  "challenges": [
    {
      "id": "c1",
      "title": "I like apples",
      "icon": "🍎",
      "data": [
        {
          "en": "I like apples.",
          "cn": "我喜欢苹果。",
          "hint": "I like + plural noun. / 我喜欢+名词复数。",
          "noise": ["likes", "apple"],
          "accept": []
        },
        {
          "en": "I like oranges.",
          "cn": "我喜欢橙子。",
          "hint": "Plural of orange is oranges. / orange 的复数是 oranges。",
          "noise": ["orange", "liking"],
          "accept": []
        },
        {
          "en": "I like strawberries, too.",
          "cn": "我也喜欢草莓。",
          "hint": "Too means 'also'. / too 表示“也”。",
          "noise": ["strawberry", "to"],
          "accept": []
        },
        {
          "en": "Mmm! Yummy, yummy food!",
          "cn": "嗯！好吃的食物！",
          "hint": "Yummy means delicious. / yummy 表示好吃。",
          "noise": ["foods", "yum"],
          "accept": []
        },
        {
          "en": "I like tomatoes.",
          "cn": "我喜欢西红柿。",
          "hint": "Plural 'tomatoes'. / 复数 'tomatoes'。",
          "noise": ["tomato", "likeing"],
          "accept": []
        },
        {
          "en": "I like eggs.",
          "cn": "我喜欢鸡蛋。",
          "hint": "Plural 'eggs'. / 复数 'eggs'。",
          "noise": ["egg", "liks"],
          "accept": []
        },
        {
          "en": "I like noodles, too.",
          "cn": "我也喜欢面条。",
          "hint": "Noodles is usually plural. / noodles 通常用复数。",
          "noise": ["noodle", "two"],
          "accept": []
        },
        {
          "en": "I like carrots.",
          "cn": "我喜欢胡萝卜。",
          "hint": "Plural 'carrots'. / 复数 'carrots'。",
          "noise": ["carrot", "liking"],
          "accept": []
        },
        {
          "en": "I like chicken and fish.",
          "cn": "我喜欢鸡肉和鱼肉。",
          "hint": "Uncountable nouns for meat. / 肉类不可数。",
          "noise": ["chickens", "fishes"],
          "accept": []
        },
        {
          "en": "I like rice, too.",
          "cn": "我也喜欢米饭。",
          "hint": "Rice is uncountable. / rice 是不可数名词。",
          "noise": ["rices", "too"],
          "accept": []
        }
      ]
    },
    {
      "id": "c2",
      "title": "A rainbow salad",
      "icon": "🥗",
      "data": [
        {
          "en": "Let's make a salad together!",
          "cn": "让我们一起做沙拉吧！",
          "hint": "Let's + base verb. / Let's + 动词原形。",
          "noise": ["makes", "making"],
          "accept": ["Let us make a salad together!"]
        },
        {
          "en": "I like tomatoes and oranges.",
          "cn": "我喜欢西红柿和橙子。",
          "hint": "Two items. / 两样东西。",
          "noise": ["tomato", "orange"],
          "accept": []
        },
        {
          "en": "I like bananas.",
          "cn": "我喜欢香蕉。",
          "hint": "Plural 'bananas'. / 复数 'bananas'。",
          "noise": ["banana", "likes"],
          "accept": []
        },
        {
          "en": "I like beans.",
          "cn": "我喜欢豆子。",
          "hint": "Plural 'beans'. / 复数 'beans'。",
          "noise": ["bean", "liking"],
          "accept": []
        },
        {
          "en": "I don't like beans.",
          "cn": "我不喜欢豆子。",
          "hint": "Negative with 'don't'. / 用 'don't' 否定。",
          "noise": ["no", "doesn't"],
          "accept": ["I do not like beans."]
        },
        {
          "en": "I like cucumbers.",
          "cn": "我喜欢黄瓜。",
          "hint": "Plural 'cucumbers'. / 复数 'cucumbers'。",
          "noise": ["cucumber", "liks"],
          "accept": []
        },
        {
          "en": "Then let's have cucumbers!",
          "cn": "那么让我们吃黄瓜吧！",
          "hint": "Let's have... / 让我们吃...。",
          "noise": ["has", "having"],
          "accept": []
        },
        {
          "en": "What about Tom?",
          "cn": "汤姆怎么样？",
          "hint": "Asking about someone else. / 询问别人。",
          "noise": ["How", "Who"],
          "accept": []
        },
        {
          "en": "He likes grapes.",
          "cn": "他喜欢葡萄。",
          "hint": "He + likes (s). / 他+动词三单形式。",
          "noise": ["like", "grap"],
          "accept": []
        },
        {
          "en": "It's a rainbow salad.",
          "cn": "这是一份彩虹沙拉。",
          "hint": "It is = It's. / It is 的缩写。",
          "noise": ["are", "rainbows"],
          "accept": ["It is a rainbow salad."]
        }
      ]
    },
    {
      "id": "c3",
      "title": "Do you like it?",
      "icon": "❓",
      "data": [
        {
          "en": "Do you like it?",
          "cn": "你喜欢它吗？",
          "hint": "Question with 'Do'. / 用 'Do' 提问。",
          "noise": ["Are", "Does"],
          "accept": []
        },
        {
          "en": "Yes, I do.",
          "cn": "是的，我喜欢。",
          "hint": "Short answer for 'Do you...?'. / 'Do you...?' 的简短回答。",
          "noise": ["am", "does"],
          "accept": []
        },
        {
          "en": "It's beautiful!",
          "cn": "它很漂亮！",
          "hint": "Exclamation. / 感叹句。",
          "noise": ["are", "beauty"],
          "accept": ["It is beautiful!"]
        },
        {
          "en": "What juice do they make?",
          "cn": "他们做了什么果汁？",
          "hint": "Asking about juice. / 询问果汁。",
          "noise": ["are", "makes"],
          "accept": []
        },
        {
          "en": "What food do your friends like?",
          "cn": "你的朋友们喜欢什么食物？",
          "hint": "Asking about others' likes. / 询问他人的喜好。",
          "noise": ["likes", "does"],
          "accept": []
        },
        {
          "en": "Hi, Xiaolei. Do you like oranges?",
          "cn": "嗨，小磊。你喜欢橙子吗？",
          "hint": "Direct question. / 直接提问。",
          "noise": ["Are", "orange"],
          "accept": []
        },
        {
          "en": "No, I don't.",
          "cn": "不，我不喜欢。",
          "hint": "Short negative answer. / 简短否定回答。",
          "noise": ["am", "doesn't"],
          "accept": ["No, I do not."]
        },
        {
          "en": "I like apples.",
          "cn": "我喜欢苹果。",
          "hint": "Plural noun. / 复数名词。",
          "noise": ["apple", "likes"],
          "accept": []
        },
        {
          "en": "I like rice cakes.",
          "cn": "我喜欢年糕。",
          "hint": "Rice cakes. / 年糕。",
          "noise": ["cake", "rices"],
          "accept": []
        },
        {
          "en": "I like noodles.",
          "cn": "我喜欢面条。",
          "hint": "Noodles is plural. / noodles 是复数。",
          "noise": ["noodle", "likes"],
          "accept": []
        }
      ]
    },
    {
      "id": "c4",
      "title": "Breakfast on the farm",
      "icon": "🚜",
      "data": [
        {
          "en": "Why do Taotao and Jiajia get up early?",
          "cn": "淘淘和佳佳为什么起得早？",
          "hint": "Asking for reason. / 询问原因。",
          "noise": ["does", "gets"],
          "accept": []
        },
        {
          "en": "Time to get up, children.",
          "cn": "该起床了，孩子们。",
          "hint": "Time to do something. / 该做某事的时间了。",
          "noise": ["Gets", "child"],
          "accept": []
        },
        {
          "en": "But it's still early.",
          "cn": "但是现在还早呢。",
          "hint": "Still means 'yet'. / still 表示“还”。",
          "noise": ["is", "already"],
          "accept": ["But it is still early."]
        },
        {
          "en": "Let's get ready for breakfast.",
          "cn": "让我们准备吃早饭吧。",
          "hint": "Get ready for... / 为...做准备。",
          "noise": ["gets", "readying"],
          "accept": ["Let us get ready for breakfast."]
        },
        {
          "en": "Do you like eggs?",
          "cn": "你们喜欢鸡蛋吗？",
          "hint": "Question for kids (plural). / 问孩子（复数）。",
          "noise": ["Are", "egg"],
          "accept": []
        },
        {
          "en": "Yes, we do.",
          "cn": "是的，我们喜欢。",
          "hint": "We + do. / 我们喜欢。",
          "noise": ["are", "does"],
          "accept": []
        },
        {
          "en": "Now we've got eggs.",
          "cn": "现在我们有鸡蛋了。",
          "hint": "We have got = We've got. / 我们有了。",
          "noise": ["has", "egg"],
          "accept": ["Now we have got eggs."]
        },
        {
          "en": "Do you like corn?",
          "cn": "你喜欢玉米吗？",
          "hint": "Corn is uncountable. / corn 是不可数名词。",
          "noise": ["corns", "Are"],
          "accept": []
        },
        {
          "en": "Do you like apples?",
          "cn": "你喜欢苹果吗？",
          "hint": "Plural 'apples'. / 复数 'apples'。",
          "noise": ["apple", "Does"],
          "accept": []
        },
        {
          "en": "No, I don't. I like grapes.",
          "cn": "不，我不喜欢。我喜欢葡萄。",
          "hint": "Negative and alternative. / 否定和喜好。",
          "noise": ["am", "grape"],
          "accept": ["No, I do not. I like grapes."]
        }
      ]
    },
    {
      "id": "c5",
      "title": "Afternoon tea",
      "icon": "☕",
      "data": [
        {
          "en": "Every week, under the tree.",
          "cn": "每周，在树下。",
          "hint": "Prepositional phrase. / 介词短语。",
          "noise": ["weeks", "trees"],
          "accept": []
        },
        {
          "en": "A nice afternoon tea for Grandpa and me!",
          "cn": "爷爷和我的一顿美妙下午茶！",
          "hint": "Afternoon tea. / 下午茶。",
          "noise": ["the", "my"],
          "accept": []
        },
        {
          "en": "Milk tea is good.",
          "cn": "奶茶很好。",
          "hint": "Subject + is. / 主语 + is。",
          "noise": ["are", "well"],
          "accept": []
        },
        {
          "en": "Cupcakes are great.",
          "cn": "杯形蛋糕太棒了。",
          "hint": "Plural subject + are. / 复数主语 + are。",
          "noise": ["is", "greater"],
          "accept": []
        },
        {
          "en": "Yummy sandwiches, with beef and eggs!",
          "cn": "好吃的三明治，配上牛肉和鸡蛋！",
          "hint": "Sandwiches is plural of sandwich. / sandwich 的复数是 sandwiches。",
          "noise": ["sandwich", "egg"],
          "accept": []
        },
        {
          "en": "I like dumplings.",
          "cn": "我喜欢饺子。",
          "hint": "Plural 'dumplings'. / 复数 'dumplings'。",
          "noise": ["dumpling", "likes"],
          "accept": []
        },
        {
          "en": "My family and I like sushi.",
          "cn": "我和我的家人喜欢寿司。",
          "hint": "My family and I = We. / 我和家人。",
          "noise": ["likes", "me"],
          "accept": []
        },
        {
          "en": "My family and I like hot dogs.",
          "cn": "我和我的家人喜欢热狗。",
          "hint": "Hot dogs. / 热狗。",
          "noise": ["dog", "am"],
          "accept": []
        },
        {
          "en": "How can I make a sandwich?",
          "cn": "我该怎么做三明治？",
          "hint": "How can I... / 我该如何...。",
          "noise": ["do", "makes"],
          "accept": []
        },
        {
          "en": "Let's get ready for lunch together, too!",
          "cn": "让我们也一起准备午饭吧！",
          "hint": "Lunch. / 午饭。",
          "noise": ["lunches", "two"],
          "accept": ["Let us get ready for lunch together, too!"]
        }
      ]
    }
  ]
}