{
  "level": "Grade 7 Semester 2 - Unit 7",
  "title": "Spelling Master",
  "spelling_words": [
    {
      "word": "museum",
      "meaning": "博物馆",
      "type": "multi-syllable",
      "chunks": [
        {
          "correct": "mu",
          "options": [
            "mu",
            "mo",
            "me"
          ]
        },
        {
          "correct": "se",
          "options": [
            "se",
            "ze",
            "si"
          ]
        },
        {
          "correct": "um",
          "options": [
            "um",
            "un",
            "am"
          ]
        }
      ],
      "id": "74dde54c"
    },
    {
      "word": "exhibition",
      "meaning": "展览",
      "type": "multi-syllable",
      "chunks": [
        {
          "correct": "ex",
          "options": [
            "ex",
            "ax",
            "ox"
          ]
        },
        {
          "correct": "hi",
          "options": [
            "hi",
            "he",
            "ha"
          ]
        },
        {
          "correct": "bi",
          "options": [
            "bi",
            "be",
            "ba"
          ]
        },
        {
          "correct": "tion",
          "options": [
            "tion",
            "sion",
            "cion"
          ]
        }
      ],
      "id": "e28bc0a5"
    },
    {
      "word": "direction",
      "meaning": "方向",
      "type": "multi-syllable",
      "chunks": [
        {
          "correct": "di",
          "options": [
            "di",
            "de",
            "da"
          ]
        },
        {
          "correct": "rec",
          "options": [
            "rec",
            "rac",
            "roc"
          ]
        },
        {
          "correct": "tion",
          "options": [
            "tion",
            "sion",
            "cion"
          ]
        }
      ],
      "id": "9fefe79f"
    },
    {
      "word": "trip",
      "meaning": "旅行",
      "type": "single-syllable",
      "chunks": [
        {
          "correct": "tr",
          "options": [
            "tr",
            "dr",
            "pr"
          ]
        },
        {
          "correct": "i",
          "options": [
            "i",
            "e",
            "a"
          ]
        },
        {
          "correct": "p",
          "options": [
            "p",
            "b",
            "t"
          ]
        }
      ],
      "id": "21d52a49"
    },
    {
      "word": "wastewater",
      "meaning": "废水",
      "type": "multi-syllable",
      "chunks": [
        {
          "correct": "waste",
          "options": [
            "waste",
            "waist",
            "west"
          ]
        },
        {
          "correct": "wa",
          "options": [
            "wa",
            "wo",
            "we"
          ]
        },
        {
          "correct": "ter",
          "options": [
            "ter",
            "tar",
            "tor"
          ]
        }
      ],
      "id": "e8644134"
    },
    {
      "word": "plant",
      "meaning": "工厂",
      "type": "single-syllable",
      "chunks": [
        {
          "correct": "pl",
          "options": [
            "pl",
            "bl",
            "cl"
          ]
        },
        {
          "correct": "a",
          "options": [
            "a",
            "o",
            "e"
          ]
        },
        {
          "correct": "nt",
          "options": [
            "nt",
            "nd",
            "mt"
          ]
        }
      ],
      "id": "d30614c4"
    },
    {
      "word": "remove",
      "meaning": "移开; 拿走",
      "type": "multi-syllable",
      "chunks": [
        {
          "correct": "re",
          "options": [
            "re",
            "ri",
            "ra"
          ]
        },
        {
          "correct": "move",
          "options": [
            "move",
            "more",
            "love"
          ]
        }
      ],
      "id": "dbd1dcbc"
    },
    {
      "word": "piece",
      "meaning": "片; 块",
      "type": "single-syllable",
      "chunks": [
        {
          "correct": "p",
          "options": [
            "p",
            "b",
            "t"
          ]
        },
        {
          "correct": "ie",
          "options": [
            "ie",
            "ei",
            "ee"
          ]
        },
        {
          "correct": "ce",
          "options": [
            "ce",
            "se",
            "ze"
          ]
        }
      ],
      "id": "22b4ef19"
    },
    {
      "word": "waste",
      "meaning": "废弃物",
      "type": "single-syllable",
      "chunks": [
        {
          "correct": "w",
          "options": [
            "w",
            "v",
            "m"
          ]
        },
        {
          "correct": "a",
          "options": [
            "a",
            "ai",
            "ay"
          ]
        },
        {
          "correct": "ste",
          "options": [
            "ste",
            "sta",
            "sti"
          ]
        }
      ],
      "id": "88ad7a68"
    },
    {
      "word": "machine",
      "meaning": "机器",
      "type": "multi-syllable",
      "chunks": [
        {
          "correct": "ma",
          "options": [
            "ma",
            "me",
            "mo"
          ]
        },
        {
          "correct": "chine",
          "options": [
            "chine",
            "shine",
            "line"
          ]
        }
      ],
      "id": "9d1faa36"
    },
    {
      "word": "germ",
      "meaning": "微生物; 细菌",
      "type": "single-syllable",
      "chunks": [
        {
          "correct": "g",
          "options": [
            "g",
            "j",
            "d"
          ]
        },
        {
          "correct": "er",
          "options": [
            "er",
            "ir",
            "ur"
          ]
        },
        {
          "correct": "m",
          "options": [
            "m",
            "n",
            "l"
          ]
        }
      ],
      "id": "222f9a8e"
    },
    {
      "word": "step",
      "meaning": "步骤; 脚步",
      "type": "single-syllable",
      "chunks": [
        {
          "correct": "st",
          "options": [
            "st",
            "sp",
            "sk"
          ]
        },
        {
          "correct": "e",
          "options": [
            "e",
            "a",
            "o"
          ]
        },
        {
          "correct": "p",
          "options": [
            "p",
            "b",
            "d"
          ]
        }
      ],
      "id": "8e088ee7"
    },
    {
      "word": "realize",
      "meaning": "认识到; 实现",
      "type": "multi-syllable",
      "chunks": [
        {
          "correct": "re",
          "options": [
            "re",
            "ri",
            "ra"
          ]
        },
        {
          "correct": "al",
          "options": [
            "al",
            "el",
            "ol"
          ]
        },
        {
          "correct": "ize",
          "options": [
            "ize",
            "ise",
            "ice"
          ]
        }
      ],
      "id": "52c10392"
    },
    {
      "word": "inside",
      "meaning": "在……里面",
      "type": "multi-syllable",
      "chunks": [
        {
          "correct": "in",
          "options": [
            "in",
            "en",
            "on"
          ]
        },
        {
          "correct": "side",
          "options": [
            "side",
            "site",
            "size"
          ]
        }
      ],
      "id": "b8e9805b"
    },
    {
      "word": "diary",
      "meaning": "日记",
      "type": "multi-syllable",
      "chunks": [
        {
          "correct": "di",
          "options": [
            "di",
            "de",
            "da"
          ]
        },
        {
          "correct": "a",
          "options": [
            "a",
            "e",
            "o"
          ]
        },
        {
          "correct": "ry",
          "options": [
            "ry",
            "ly",
            "ty"
          ]
        }
      ],
      "id": "084ffb7c"
    },
    {
      "word": "agree",
      "meaning": "同意",
      "type": "multi-syllable",
      "chunks": [
        {
          "correct": "a",
          "options": [
            "a",
            "u",
            "o"
          ]
        },
        {
          "correct": "gree",
          "options": [
            "gree",
            "tree",
            "free"
          ]
        }
      ],
      "id": "15731a4f"
    },
    {
      "word": "process",
      "meaning": "过程",
      "type": "multi-syllable",
      "chunks": [
        {
          "correct": "pro",
          "options": [
            "pro",
            "pre",
            "per"
          ]
        },
        {
          "correct": "cess",
          "options": [
            "cess",
            "sess",
            "less"
          ]
        }
      ],
      "id": "a31409b0"
    },
    {
      "word": "theatre",
      "meaning": "剧场",
      "type": "multi-syllable",
      "chunks": [
        {
          "correct": "the",
          "options": [
            "the",
            "tha",
            "thi"
          ]
        },
        {
          "correct": "a",
          "options": [
            "a",
            "e",
            "i"
          ]
        },
        {
          "correct": "tre",
          "options": [
            "tre",
            "ter",
            "tra"
          ]
        }
      ],
      "id": "e1fe922c"
    },
    {
      "word": "factory",
      "meaning": "工厂",
      "type": "multi-syllable",
      "chunks": [
        {
          "correct": "fac",
          "options": [
            "fac",
            "fec",
            "fic"
          ]
        },
        {
          "correct": "to",
          "options": [
            "to",
            "tu",
            "ta"
          ]
        },
        {
          "correct": "ry",
          "options": [
            "ry",
            "ly",
            "ty"
          ]
        }
      ],
      "id": "d7170219"
    },
    {
      "word": "terrible",
      "meaning": "糟糕的",
      "type": "multi-syllable",
      "chunks": [
        {
          "correct": "ter",
          "options": [
            "ter",
            "tar",
            "tor"
          ]
        },
        {
          "correct": "ri",
          "options": [
            "ri",
            "re",
            "ra"
          ]
        },
        {
          "correct": "ble",
          "options": [
            "ble",
            "dle",
            "ple"
          ]
        }
      ],
      "id": "569cf965"
    },
    {
      "word": "actor",
      "meaning": "演员",
      "type": "multi-syllable",
      "chunks": [
        {
          "correct": "ac",
          "options": [
            "ac",
            "oc",
            "ec"
          ]
        },
        {
          "correct": "tor",
          "options": [
            "tor",
            "ter",
            "tar"
          ]
        }
      ],
      "id": "7b3efcdb"
    },
    {
      "word": "gun",
      "meaning": "枪",
      "type": "single-syllable",
      "chunks": [
        {
          "correct": "g",
          "options": [
            "g",
            "j",
            "k"
          ]
        },
        {
          "correct": "u",
          "options": [
            "u",
            "o",
            "a"
          ]
        },
        {
          "correct": "n",
          "options": [
            "n",
            "m",
            "l"
          ]
        }
      ],
      "id": "1cf72103"
    },
    {
      "word": "along",
      "meaning": "沿着",
      "type": "multi-syllable",
      "chunks": [
        {
          "correct": "a",
          "options": [
            "a",
            "o",
            "u"
          ]
        },
        {
          "correct": "long",
          "options": [
            "long",
            "song",
            "tong"
          ]
        }
      ],
      "id": "681424bb"
    },
    {
      "word": "road",
      "meaning": "道路",
      "type": "single-syllable",
      "chunks": [
        {
          "correct": "r",
          "options": [
            "r",
            "l",
            "w"
          ]
        },
        {
          "correct": "oa",
          "options": [
            "oa",
            "ou",
            "ow"
          ]
        },
        {
          "correct": "d",
          "options": [
            "d",
            "t",
            "b"
          ]
        }
      ],
      "id": "079d22c2"
    },
    {
      "word": "create",
      "meaning": "创造",
      "type": "multi-syllable",
      "chunks": [
        {
          "correct": "cre",
          "options": [
            "cre",
            "cra",
            "cri"
          ]
        },
        {
          "correct": "ate",
          "options": [
            "ate",
            "ite",
            "ute"
          ]
        }
      ],
      "id": "d1e3a2bb"
    },
    {
      "word": "record",
      "meaning": "记录",
      "type": "multi-syllable",
      "chunks": [
        {
          "correct": "re",
          "options": [
            "re",
            "ri",
            "ra"
          ]
        },
        {
          "correct": "cord",
          "options": [
            "cord",
            "card",
            "word"
          ]
        }
      ],
      "id": "926847d1"
    },
    {
      "word": "skill",
      "meaning": "技能",
      "type": "single-syllable",
      "chunks": [
        {
          "correct": "sk",
          "options": [
            "sk",
            "sc",
            "st"
          ]
        },
        {
          "correct": "i",
          "options": [
            "i",
            "e",
            "u"
          ]
        },
        {
          "correct": "ll",
          "options": [
            "ll",
            "ss",
            "tt"
          ]
        }
      ],
      "id": "a0d746d3"
    },
    {
      "word": "explore",
      "meaning": "探索",
      "type": "multi-syllable",
      "chunks": [
        {
          "correct": "ex",
          "options": [
            "ex",
            "ax",
            "ox"
          ]
        },
        {
          "correct": "plore",
          "options": [
            "plore",
            "store",
            "chore"
          ]
        }
      ],
      "id": "40b8de97"
    },
    {
      "word": "tent",
      "meaning": "帐篷",
      "type": "single-syllable",
      "chunks": [
        {
          "correct": "t",
          "options": [
            "t",
            "d",
            "p"
          ]
        },
        {
          "correct": "e",
          "options": [
            "e",
            "a",
            "o"
          ]
        },
        {
          "correct": "nt",
          "options": [
            "nt",
            "nd",
            "mp"
          ]
        }
      ],
      "id": "b0fba3c1"
    },
    {
      "word": "cucumber",
      "meaning": "黄瓜",
      "type": "multi-syllable",
      "chunks": [
        {
          "correct": "cu",
          "options": [
            "cu",
            "co",
            "ce"
          ]
        },
        {
          "correct": "cum",
          "options": [
            "cum",
            "com",
            "cam"
          ]
        },
        {
          "correct": "ber",
          "options": [
            "ber",
            "der",
            "ter"
          ]
        }
      ],
      "id": "dd17a906"
    },
    {
      "word": "straight",
      "meaning": "直接地",
      "type": "single-syllable",
      "chunks": [
        {
          "correct": "str",
          "options": [
            "str",
            "spr",
            "scr"
          ]
        },
        {
          "correct": "ai",
          "options": [
            "ai",
            "ay",
            "ei"
          ]
        },
        {
          "correct": "ght",
          "options": [
            "ght",
            "cht",
            "tht"
          ]
        }
      ],
      "id": "a304ad13"
    },
    {
      "word": "fill",
      "meaning": "装满",
      "type": "single-syllable",
      "chunks": [
        {
          "correct": "f",
          "options": [
            "f",
            "v",
            "p"
          ]
        },
        {
          "correct": "i",
          "options": [
            "i",
            "e",
            "a"
          ]
        },
        {
          "correct": "ll",
          "options": [
            "ll",
            "ss",
            "ff"
          ]
        }
      ],
      "id": "c34706ce"
    },
    {
      "word": "basket",
      "meaning": "篮子",
      "type": "multi-syllable",
      "chunks": [
        {
          "correct": "bas",
          "options": [
            "bas",
            "pas",
            "das"
          ]
        },
        {
          "correct": "ket",
          "options": [
            "ket",
            "get",
            "let"
          ]
        }
      ],
      "id": "8c55881a"
    },
    {
      "word": "branch",
      "meaning": "树枝",
      "type": "single-syllable",
      "chunks": [
        {
          "correct": "br",
          "options": [
            "br",
            "pr",
            "gr"
          ]
        },
        {
          "correct": "a",
          "options": [
            "a",
            "u",
            "o"
          ]
        },
        {
          "correct": "nch",
          "options": [
            "nch",
            "nsh",
            "nzh"
          ]
        }
      ],
      "id": "8237c7f7"
    },
    {
      "word": "leaf",
      "meaning": "叶子",
      "type": "single-syllable",
      "chunks": [
        {
          "correct": "l",
          "options": [
            "l",
            "r",
            "n"
          ]
        },
        {
          "correct": "ea",
          "options": [
            "ea",
            "ee",
            "ie"
          ]
        },
        {
          "correct": "f",
          "options": [
            "f",
            "v",
            "th"
          ]
        }
      ],
      "id": "a0e37145"
    },
    {
      "word": "finally",
      "meaning": "终于",
      "type": "multi-syllable",
      "chunks": [
        {
          "correct": "fi",
          "options": [
            "fi",
            "fy",
            "fe"
          ]
        },
        {
          "correct": "nal",
          "options": [
            "nal",
            "nel",
            "nol"
          ]
        },
        {
          "correct": "ly",
          "options": [
            "ly",
            "ty",
            "ry"
          ]
        }
      ],
      "id": "2b1ecbb7"
    },
    {
      "word": "grain",
      "meaning": "谷物",
      "type": "single-syllable",
      "chunks": [
        {
          "correct": "gr",
          "options": [
            "gr",
            "br",
            "dr"
          ]
        },
        {
          "correct": "ai",
          "options": [
            "ai",
            "ay",
            "ei"
          ]
        },
        {
          "correct": "n",
          "options": [
            "n",
            "m",
            "l"
          ]
        }
      ],
      "id": "11364a9d"
    },
    {
      "word": "fresh",
      "meaning": "新鲜的",
      "type": "single-syllable",
      "chunks": [
        {
          "correct": "fr",
          "options": [
            "fr",
            "pr",
            "gr"
          ]
        },
        {
          "correct": "e",
          "options": [
            "e",
            "a",
            "o"
          ]
        },
        {
          "correct": "sh",
          "options": [
            "sh",
            "ch",
            "th"
          ]
        }
      ],
      "id": "095da596"
    },
    {
      "word": "certainly",
      "meaning": "肯定地",
      "type": "multi-syllable",
      "chunks": [
        {
          "correct": "cer",
          "options": [
            "cer",
            "cur",
            "cir"
          ]
        },
        {
          "correct": "tain",
          "options": [
            "tain",
            "tion",
            "sion"
          ]
        },
        {
          "correct": "ly",
          "options": [
            "ly",
            "ty",
            "ry"
          ]
        }
      ],
      "id": "61a7f59a"
    },
    {
      "word": "entry",
      "meaning": "日记一则",
      "type": "multi-syllable",
      "chunks": [
        {
          "correct": "en",
          "options": [
            "en",
            "an",
            "in"
          ]
        },
        {
          "correct": "try",
          "options": [
            "try",
            "cry",
            "dry"
          ]
        }
      ],
      "id": "a513f957"
    }
  ]
}