{
  "level": "Grade 6 Semester 2",
  "part": "Module 7",
  "tree": {
    "id": "root",
    "text": "Module 7",
    "emoji": "🚀",
    "state": "emoji",
    "children": [
      {
        "id": "stories",
        "text": "Stories",
        "emoji": "📖",
        "state": "hidden",
        "children": [
          {
            "id": "yang",
            "text": "Yang Liwei",
            "emoji": "👨‍🚀",
            "state": "hidden",
            "children": [
              { "id": "yang_1", "text": "Famous taikonaut (著名宇航员)", "emoji": "🇨🇳", "state": "hidden", "children": [] },
              { "id": "yang_2", "text": "Flew into space Oct 2003 (2003年10月飞向太空)", "emoji": "📅", "state": "hidden", "children": [] },
              { "id": "yang_3", "text": "Spent 21 hours (度过21小时)", "emoji": "⌛", "state": "hidden", "children": [] }
            ]
          },
          {
            "id": "helen",
            "text": "Helen Keller",
            "emoji": "👩‍🏫",
            "state": "hidden",
            "children": [
              { "id": "helen_1", "text": "Blind and deaf as baby (幼时盲聋)", "emoji": "🔇", "state": "hidden", "children": [] },
              { "id": "helen_2", "text": "Anne Sullivan taught her (老师教导)", "emoji": "🤝", "state": "hidden", "children": [] },
              { "id": "helen_3", "text": "Role model for all (大家的榜样)", "emoji": "🏆", "state": "hidden", "children": [] }
            ]
          }
        ]
      },
      {
        "id": "vocab",
        "text": "Vocabulary",
        "emoji": "🔤",
        "state": "hidden",
        "children": [
          {
            "id": "v_verbs",
            "text": "Verbs (动作)",
            "emoji": "🏃",
            "state": "hidden",
            "children": [
              { "id": "v1", "text": "spent (度过)", "emoji": "⌛", "state": "hidden", "children": [] },
              { "id": "v2", "text": "flew (飞)", "emoji": "✈️", "state": "hidden", "children": [] },
              { "id": "v3", "text": "spell (拼写)", "emoji": "✍️", "state": "hidden", "children": [] },
              { "id": "v4", "text": "became (变成)", "emoji": "🔄", "state": "hidden", "children": [] }
            ]
          },
          {
            "id": "v_nouns",
            "text": "Nouns (事物)",
            "emoji": "🍎",
            "state": "hidden",
            "children": [
              { "id": "n1", "text": "taikonaut (宇航员)", "emoji": "👨‍🚀", "state": "hidden", "children": [] },
              { "id": "n2", "text": "video (录像)", "emoji": "📹", "state": "hidden", "children": [] },
              { "id": "n3", "text": "airport (机场)", "emoji": "🛫", "state": "hidden", "children": [] },
              { "id": "n4", "text": "letter (字母)", "emoji": "🅰️", "state": "hidden", "children": [] }
            ]
          },
          {
            "id": "v_phrases",
            "text": "Phrases (短语)",
            "emoji": "🔗",
            "state": "hidden",
            "children": [
              { "id": "p1", "text": "all over (到处)", "emoji": "🌍", "state": "hidden", "children": [] },
              { "id": "p2", "text": "role model (榜样)", "emoji": "🥇", "state": "hidden", "children": [] },
              { "id": "p3", "text": "proud of (自豪)", "emoji": "😊", "state": "hidden", "children": [] }
            ]
          }
        ]
      },
      {
        "id": "grammar",
        "text": "Grammar Focus",
        "emoji": "⚖️",
        "state": "hidden",
        "children": [
          {
            "id": "g1",
            "text": "Past Tense (过去式)",
            "emoji": "🕰️",
            "state": "hidden",
            "children": [
              { "id": "g1_1", "text": "He spent 21 hours.", "emoji": "✅", "state": "hidden", "children": [] },
              { "id": "g1_2", "text": "He flew into space.", "emoji": "🚀", "state": "hidden", "children": [] }
            ]
          },
          {
            "id": "g2",
            "text": "Abilities (能力)",
            "emoji": "💪",
            "state": "hidden",
            "children": [
              { "id": "g2_1", "text": "She couldn't see.", "emoji": "🚫", "state": "hidden", "children": [] },
              { "id": "g2_2", "text": "She could talk.", "emoji": "🗣️", "state": "hidden", "children": [] }
            ]
          }
        ]
      }
    ]
  }
}
