{
  "level": "Grade 5 Semester 2",
  "part": "Unit 6",
  "section": "Model Essay 1",
  "tree": {
    "id": "root",
    "text": "Changes in My School",
    "emoji": "🏫",
    "cn": "我学校的变化",
    "children": [
      {
        "id": "intro",
        "text": "Background (背景)",
        "emoji": "📍",
        "children": [
          {
            "id": "s1",
            "text": "I found an old photo of my school.",
            "cn": "我发现了一张我学校的老照片。",
            "emoji": "📷",
            "notes": "found: 发现（find的过去式）",
            "statement": "found 是不规则动词过去式。",
            "answer": true,
            "explanation": "find 的过去式是 found。",
            "keywords": "found, photo, school",
            "children": [
              {
                "id": "s2",
                "text": "It looks very different now.",
                "cn": "它现在看起来非常不同。",
                "emoji": "✨",
                "notes": "different: 不同的",
                "statement": "looks 是连系动词，后面接形容词不同。",
                "answer": true,
                "explanation": "look different 意为“看起来不同”。",
                "keywords": "looks, different",
                "children": []
              }
            ]
          }
        ]
      },
      {
        "id": "c1",
        "text": "Buildings (建筑对比)",
        "emoji": "🏗️",
        "children": [
          {
            "id": "s3",
            "text": "In the past, the school building was small and old.",
            "cn": "在过去，教学楼又小又旧。",
            "emoji": "🏚️",
            "notes": "in the past: 在过去",
            "statement": "was 是用于单数主语 building 的过去式。",
            "answer": true,
            "explanation": "描述过去的状态。",
            "keywords": "past, building, small, old",
            "children": [
              {
                "id": "s4",
                "text": "Today, it is big and new.",
                "cn": "今天，它又大又新。",
                "emoji": "🏢",
                "notes": "today: 今天",
                "statement": "这个句子使用了一般现在时 is。",
                "answer": true,
                "explanation": "描述现在的状态。",
                "keywords": "today, big, new",
                "children": []
              }
            ]
          }
        ]
      },
      {
        "id": "c2",
        "text": "Playgrounds (操场对比)",
        "emoji": "🏃",
        "children": [
          {
            "id": "s5",
            "text": "There was only one playground before.",
            "cn": "以前只有一个操场。",
            "emoji": "🏟️",
            "notes": "before: 以前",
            "statement": "There was 意为“有（过去）”。",
            "answer": true,
            "explanation": "用于单数名词 playground。",
            "keywords": "was, one, playground",
            "children": [
              {
                "id": "s6",
                "text": "Now we have two big playgrounds.",
                "cn": "现在我们有两个大操场。",
                "emoji": "🏟️🏟️",
                "notes": "have: 有",
                "statement": "have 用于复数主语 we。",
                "answer": true,
                "explanation": "一般现在时用法。",
                "keywords": "now, have, two, playgrounds",
                "children": []
              }
            ]
          }
        ]
      },
      {
        "id": "c3",
        "text": "Facilities (设施对比)",
        "emoji": "💻",
        "children": [
          {
            "id": "s7",
            "text": "Classrooms did not have computers in the past.",
            "cn": "过去教室里没有电脑。",
            "emoji": "📽️",
            "notes": "did not have: 没有（过去）",
            "statement": "did not have 是 have 的否定过去式。",
            "answer": true,
            "explanation": "使用助动词 did 构成否定。",
            "keywords": "past, classrooms, computers",
            "children": [
              {
                "id": "s8",
                "text": "But every classroom has computers now.",
                "cn": "但现在每个教室都有电脑。",
                "emoji": "🖥️",
                "notes": "every: 每个",
                "highlight": "But",
                "statement": "every classroom 后接动词单三形式 has。",
                "answer": true,
                "explanation": "every 修饰单数名词作主语。",
                "keywords": "every, classroom, has",
                "children": []
              }
            ]
          }
        ]
      },
      {
        "id": "reflect",
        "text": "Reflection (感悟)",
        "emoji": "💡",
        "children": [
          {
            "id": "s9",
            "text": "I am very happy with the changes.",
            "cn": "我对这些变化感到非常开心。",
            "emoji": "😊",
            "notes": "changes: 变化",
            "statement": "be happy with 意为“对...感到满意/开心”。",
            "answer": true,
            "explanation": "固定搭配。",
            "keywords": "happy, changes",
            "children": [
              {
                "id": "s10",
                "text": "My school is much better now.",
                "cn": "我的学校现在好多了。",
                "emoji": "🌈",
                "notes": "much better: 好得多",
                "statement": "much better 意为“好得多”。",
                "answer": true,
                "explanation": "much 修饰比较级 better。",
                "keywords": "school, better",
                "children": []
              }
            ]
          }
        ]
      }
    ]
  }
}
