{
  "level": "Grade 5 Semester 2",
  "part": "Unit 6",
  "section": "Model Essay 2",
  "tree": {
    "id": "root",
    "text": "Changes in My School",
    "emoji": "🌟",
    "cn": "我学校的变化",
    "children": [
      {
        "id": "intro",
        "text": "Background (背景)",
        "emoji": "📍",
        "children": [
          {
            "id": "p1",
            "text": "I recently found an old photo of my school, and it looks completely different now.",
            "cn": "我最近发现了一张我学校的老照片，它现在看起来完全不同了。",
            "emoji": "📷",
            "notes": "completely: 完全地；different: 不同的",
            "highlight": "completely different",
            "statement": "completely 是副词，用来修饰形容词 different。",
            "answer": true,
            "explanation": "表示程度。",
            "keywords": "recently, photo, different",
            "children": []
          }
        ]
      },
      {
        "id": "c1",
        "text": "Buildings (建筑对比)",
        "emoji": "🏗️",
        "children": [
          {
            "id": "p2",
            "text": "In the past, the school building was small and old, but today it is big and modern.",
            "cn": "在过去，教学楼又小又旧，但今天它既大又现代。",
            "emoji": "🏢",
            "notes": "modern: 现代的",
            "highlight": "but",
            "statement": "modern 意为“现代的”，是 old 的反义词。",
            "answer": true,
            "explanation": "用来描述新建筑的特点。",
            "keywords": "building, modern",
            "children": []
          }
        ]
      },
      {
        "id": "c2",
        "text": "Playgrounds (操场对比)",
        "emoji": "🏃",
        "children": [
          {
            "id": "p3",
            "text": "We used to have only one small playground, but now we have two big ones for sports.",
            "cn": "我们过去只有一个小操场，但现在我们有两个大的用于运动。",
            "emoji": "🏟️",
            "notes": "used to: 过去常常；ones: 指代 playgrounds",
            "highlight": "used to, but",
            "statement": "used to have 意为“过去曾有（现在没了）”。",
            "answer": true,
            "explanation": "描述过去的状态。",
            "keywords": "used to, playground, sports",
            "children": []
          }
        ]
      },
      {
        "id": "c3",
        "text": "Facilities (设施对比)",
        "emoji": "💻",
        "children": [
          {
            "id": "p4",
            "text": "The classrooms didn't have any computers or smart boards in the old days.",
            "cn": "在以前的日子里，教室里没有任何电脑或智能白板。",
            "emoji": "📽️",
            "notes": "smart boards: 智能白板；in the old days: 在过去",
            "statement": "didn't have any 用于否定句表示“没有任何”。",
            "answer": true,
            "explanation": "any 通常用于否定句和疑问句。",
            "keywords": "classrooms, smart boards, old days",
            "children": [
              {
                "id": "p5",
                "text": "However, every classroom is now full of high-tech equipment.",
                "cn": "然而，现在每个教室都充满了高科技设备。",
                "emoji": "🖥️",
                "notes": "however: 然而；be full of: 充满；equipment: 设备",
                "highlight": "However, be full of",
                "statement": "however 表示转折，通常用逗号隔开。",
                "answer": true,
                "explanation": "副词，意为“然而”。",
                "keywords": "however, every, equipment",
                "children": []
              }
            ]
          }
        ]
      },
      {
        "id": "c4",
        "text": "Library & Gym (新增设施)",
        "emoji": "📖",
        "children": [
          {
            "id": "p6",
            "text": "We also have a new library and a gym where we can enjoy our school life.",
            "cn": "我们还有一个新的图书馆和一个体育馆，在那里我们可以享受我们的学校生活。",
            "emoji": "🏀",
            "notes": "gym: 体育馆；where: 在那里（引导从句）",
            "highlight": "where",
            "statement": "gym 是 gymnasium 的缩写。",
            "answer": true,
            "explanation": "意为“体育馆”。",
            "keywords": "library, gym, enjoy",
            "children": []
          }
        ]
      },
      {
        "id": "reflect",
        "text": "Reflection (感悟)",
        "emoji": "💡",
        "children": [
          {
            "id": "p7",
            "text": "I am absolutely happy with these amazing changes.",
            "cn": "我对这些惊人的变化感到绝对开心。",
            "emoji": "🤩",
            "notes": "absolutely: 绝对地；amazing: 惊人的",
            "highlight": "absolutely, amazing",
            "statement": "absolutely 是副词，意为“绝对地”。",
            "answer": true,
            "explanation": "加强语气。",
            "keywords": "absolutely, happy, amazing",
            "children": [
              {
                "id": "p8",
                "text": "I realized that our school is becoming much better and more modern every day.",
                "cn": "我意识到我们的学校每天都变得更好、更现代。",
                "emoji": "📈",
                "notes": "realized: 意识到；becoming: 变得",
                "highlight": "realized that, becoming",
                "statement": "becoming 意为“正在变得”。",
                "answer": true,
                "explanation": "表示一种持续的变化过程。",
                "keywords": "realized, becoming, modern",
                "children": []
              }
            ]
          }
        ]
      }
    ]
  }
}
