{
  "level": "Grade 7 Semester 1",
  "part": "Unit 7",
  "sections": [
    {
      "section": "Model Essay Basic",
      "tree": {
        "id": "root",
        "text": "My Birthday Celebration",
        "cn": "我的生日庆祝",
        "emoji": "🎂",
        "children": [
          {
            "id": "b_para1",
            "text": "Morning Activities",
            "cn": "早上的活动",
            "emoji": "📁",
            "children": [
              {
                "id": "b_s1",
                "text": "Today is my 13th birthday, and I am very excited.",
                "cn": "今天是我的13岁生日，我非常兴奋。",
                "notes": "13th birthday: 13岁生日; excited: 兴奋的",
                "statement": "作者今天过了12岁生日。",
                "answer": false,
                "explanation": "句子中明确提到今天是作者的13岁生日（13th birthday）。",
                "emoji": "🥳",
                "keywords": "Today, 13th, birthday, excited",
                "highlight": "and",
                "children": []
              },
              {
                "id": "b_s2",
                "text": "After breakfast, my mum and I went to the supermarket.",
                "cn": "早餐后，我妈妈和我去了超市。",
                "notes": "after breakfast: 早餐后; supermarket: 超市",
                "statement": "作者是在早餐后去超市的。",
                "answer": true,
                "explanation": "句子中提到“After breakfast”（早餐后），作者和妈妈去了超市。",
                "emoji": "🛒",
                "keywords": "After breakfast, mum, went to, supermarket",
                "highlight": "After",
                "children": []
              },
              {
                "id": "b_s3",
                "text": "We saw a lot of things there and bought food, fruit, and a big birthday cake.",
                "cn": "我们在那里看到了很多东西，并买了食物、水果和一个大生日蛋糕。",
                "notes": "a lot of: 许多; bought: 买（buy的过去式）; birthday cake: 生日蛋糕",
                "statement": "“bought” 是动词 “buy” 的过去式形式。",
                "answer": true,
                "explanation": "buy 的过去式是不规则变化，为 bought，表示过去发生的购买动作。",
                "emoji": "🍰",
                "keywords": "saw, a lot of, bought, food, cake",
                "highlight": "and, and",
                "children": []
              }
            ]
          },
          {
            "id": "b_para2",
            "text": "Evening Dinner & Gifts",
            "cn": "晚上的晚餐与礼物",
            "emoji": "📁",
            "children": [
              {
                "id": "b_s4",
                "text": "In the evening, my family had a big dinner together at home.",
                "cn": "晚上，我们全家一起在家里吃了一顿丰盛的晚餐。",
                "notes": "in the evening: 在晚上; had a big dinner: 吃了一顿大餐; together: 一起",
                "statement": "作者一家人是在餐馆里吃晚餐的。",
                "answer": false,
                "explanation": "句子中提到“at home”（在家里），说明他们是在家里吃大餐的。",
                "emoji": "🍽️",
                "keywords": "evening, family, had, big dinner, home",
                "highlight": "",
                "children": []
              },
              {
                "id": "b_s5",
                "text": "I got many birthday gifts from my parents and friends.",
                "cn": "我从我父母和朋友那里得到了许多生日礼物。",
                "notes": "got: 得到（get的过去式）; birthday gifts: 生日礼物; parents: 父母",
                "statement": "“gifts” 在这里是复数形式，意为“礼物”。",
                "answer": true,
                "explanation": "gift 是可数名词，复数形式直接在词尾加 -s，变为 gifts。",
                "emoji": "🎁",
                "keywords": "got, many, birthday gifts, parents, friends",
                "highlight": "",
                "children": []
              }
            ]
          },
          {
            "id": "b_para3",
            "text": "Birthday Wish & Feelings",
            "cn": "许愿与感受",
            "emoji": "📁",
            "children": [
              {
                "id": "b_s6",
                "text": "Then, I made a wish and blew out the candles.",
                "cn": "然后，我许了一个愿并吹灭了蜡烛。",
                "notes": "make a wish: 许愿; blow out: 吹灭; candles: 蜡烛",
                "statement": "“blew” 是动词 “blow” 的过去式形式。",
                "answer": true,
                "explanation": "blow 的过去式是不规则变化，为 blew，意为“吹”。",
                "emoji": "🕯️",
                "keywords": "Then, made a wish, blew out, candles",
                "highlight": "Then, and",
                "children": []
              },
              {
                "id": "b_s7",
                "text": "We also took a photo together to celebrate this special day.",
                "cn": "我们还一起拍了一张照片来庆祝这个特别的日子。",
                "notes": "took a photo: 拍照; celebrate: 庆祝; special day: 特别的日子",
                "statement": "句子中的 “celebrate” 意为“惩罚”。",
                "answer": false,
                "explanation": "“celebrate” 意为“庆祝，庆贺”，而不是“惩罚”。",
                "emoji": "📸",
                "keywords": "also, took a photo, celebrate, special day",
                "highlight": "also, to",
                "children": []
              },
              {
                "id": "b_s8",
                "text": "I had a wonderful time, and it was a happy day for me.",
                "cn": "我度过了一段美妙的时光，这对我来说是快乐的一天。",
                "notes": "had a wonderful time: 度过美妙时光; happy day: 快乐的一天",
                "statement": "作者觉得这个生日过得很糟糕。",
                "answer": false,
                "explanation": "作者提到“had a wonderful time”和“happy day”，说明生日过得很开心。 ",
                "emoji": "😊",
                "keywords": "had, wonderful time, happy day, for me",
                "highlight": "and",
                "children": []
              }
            ]
          }
        ]
      }
    },
    {
      "section": "Model Essay Advanced",
      "tree": {
        "id": "root_adv",
        "text": "An Unforgettable Birthday",
        "cn": "难忘的生日",
        "emoji": "🎂",
        "children": [
          {
            "id": "a_para1",
            "text": "Morning Activities",
            "cn": "早上的活动",
            "emoji": "📁",
            "children": [
              {
                "id": "a_s1",
                "text": "Today is my 13th birthday, which is a very special day for me.",
                "cn": "今天是我的13岁生日，这对我来说是一个非常特别的日子。",
                "notes": "which is...: 关系代词which引导的非限制性定语从句，修饰13th birthday",
                "statement": "句子中的 'which' 引导定语从句，修饰前面的 '13th birthday'。",
                "answer": true,
                "explanation": "'which' 在这里作为引导词，修饰主句的 '13th birthday' 并作定语从句的主语。",
                "emoji": "🎉",
                "keywords": "Today, 13th birthday, which, special day",
                "highlight": "which",
                "children": []
              },
              {
                "id": "a_s2",
                "text": "Right after breakfast, my mother and I headed to the local supermarket to prepare for the party.",
                "cn": "早餐过后，我妈妈和我前往当地的超市，为聚会做准备。",
                "notes": "right after: 就在……之后; headed to: 前往，朝……走去; prepare for: 为……做准备",
                "statement": "“headed to” 在句中表示“前往某地”。",
                "answer": true,
                "explanation": "head 在这里是动词，意为“朝……方向行进”或“前往”。",
                "emoji": "🛒",
                "keywords": "Right after, breakfast, headed to, supermarket, prepare",
                "highlight": "Right after, to",
                "children": []
              },
              {
                "id": "a_s3",
                "text": "We saw a wide variety of things and bought plenty of food, drinks, and a delicious birthday cake.",
                "cn": "我们看到了琳琅满目的商品，并买了充足的食物、饮料和一个美味的生日蛋糕。",
                "notes": "a wide variety of: 琳琅满目的，各种各样的; plenty of: 充足的，大量的; delicious: 美味的",
                "statement": "“plenty of” 只能修饰不可数名词。",
                "answer": false,
                "explanation": "“plenty of” 既可以修饰可数名词复数（如 food），也可以修饰不可数名词（如 drinks）。",
                "emoji": "🍰",
                "keywords": "wide variety, bought, plenty of, delicious, cake",
                "highlight": "and, and",
                "children": []
              }
            ]
          },
          {
            "id": "a_para2",
            "text": "Evening Dinner & Gifts",
            "cn": "晚上的晚餐与礼物",
            "emoji": "📁",
            "children": [
              {
                "id": "a_s4",
                "text": "In the evening, my family gathered together to have a big dinner, which was extremely delicious.",
                "cn": "晚上，我们全家聚集在一起吃了一顿大餐，这顿大餐极其美味。",
                "notes": "gathered: 聚集，合拢（gather的过去式）; extremely: 极其，非常; which was...: 引导非限制性定语从句，修饰a big dinner",
                "statement": "“extremely” 是一个形容词，意为“极端的”。",
                "answer": false,
                "explanation": "“extremely” 是副词，意为“极其地，非常地”，用来修饰形容词 delicious。",
                "emoji": "🍽️",
                "keywords": "evening, family, gathered, big dinner, extremely, delicious",
                "highlight": "which",
                "children": []
              },
              {
                "id": "a_s5",
                "text": "In addition, I was excited to receive many beautiful birthday gifts from my family and friends.",
                "cn": "此外，我很兴奋收到来自家人和朋友的许多精美的生日礼物。",
                "notes": "In addition: 此外，另外; receive: 收到，接纳; be excited to do: 很兴奋做某事",
                "statement": "“In addition” 是一个过渡词，表示递进或补充关系。",
                "answer": true,
                "explanation": "“In addition” 意为“此外”，常放在句首作状语，用于连接上下文，增添新的信息点。",
                "emoji": "🎁",
                "keywords": "In addition, excited, receive, beautiful, gifts",
                "highlight": "In addition, to",
                "children": []
              }
            ]
          },
          {
            "id": "a_para3",
            "text": "Birthday Wish & Feelings",
            "cn": "许愿与感受",
            "emoji": "📁",
            "children": [
              {
                "id": "a_s6",
                "text": "After singing the birthday song, I made a wish and blew out the candles on the cake.",
                "cn": "在唱完生日歌后，我许了一个愿，并吹灭了蛋糕上的蜡烛。",
                "notes": "singing: 唱歌（动名词形式，作after的宾语）; make a wish: 许愿; blow out: 吹灭",
                "statement": "这里的 “singing” 是现在分词作定语。",
                "answer": false,
                "explanation": "在介词 “After” 之后， “singing” 是动名词形式，作介词的宾语。",
                "emoji": "🕯️",
                "keywords": "After, singing, birthday song, made a wish, blew out",
                "highlight": "After, and",
                "children": []
              },
              {
                "id": "a_s7",
                "text": "To remember this celebration, we took a family photo under the bright lights.",
                "cn": "为了记住这次庆祝活动，我们在明亮的灯光下拍了一张全家福。",
                "notes": "To remember: 为了记住（动词不定式表目的）; celebration: 庆祝，庆典; family photo: 全家福",
                "statement": "句首的 “To remember...” 是不定式短语作目的状语。",
                "answer": true,
                "explanation": "不定式 To remember 放在句首，用逗号隔开，表示做后面事情的目的。",
                "emoji": "📸",
                "keywords": "To remember, celebration, took, family photo, lights",
                "highlight": "To",
                "children": []
              },
              {
                "id": "a_s8",
                "text": "Although I am now one year older, I feel very lucky to have such a warm family.",
                "cn": "虽然我现在大了一岁，但能有这样一个温暖的家庭，我感到非常幸运。",
                "notes": "Although: 虽然; one year older: 大了一岁; feel lucky to: 感到幸运去……; such a: 如此的，这样的",
                "statement": "句中的 “Although” 引导原因状语从句。",
                "answer": false,
                "explanation": "“Although” 引导的是让步状语从句，意为“虽然，尽管”。",
                "emoji": "❤️",
                "keywords": "Although, older, feel lucky, warm family",
                "highlight": "Although, to",
                "children": []
              }
            ]
          }
        ]
      }
    }
  ]
}
