{
  "level": "Grade 7 Semester 2",
  "part": "Unit 2",
  "tree": {
    "id": "root",
    "text": "Unit 2 No Rules, No Order",
    "emoji": "📏",
    "state": "emoji",
    "children": [
      {
        "id": "stories",
        "text": "Stories",
        "emoji": "📖",
        "children": [
          {
            "id": "s1",
            "text": "Tom's First Day",
            "emoji": "🎒",
            "children": [
              { "id": "s1_1", "text": "Anne helps Tom with a pen", "emoji": "🖊️", "children": [] },
              { "id": "s1_2", "text": "Learning classroom rules", "emoji": "🚫", "children": [] }
            ]
          },
          {
            "id": "s2",
            "text": "Letters to Dr Know",
            "emoji": "✉️",
            "children": [
              { "id": "s2_1", "text": "Alice feels awful about rules", "emoji": "😫", "children": [] },
              { "id": "s2_2", "text": "Dr Know's advice: Better person", "emoji": "🌟", "children": [] }
            ]
          }
        ]
      },
      {
        "id": "vocabulary",
        "text": "Vocabulary",
        "emoji": "🔤",
        "children": [
          {
            "id": "v_v",
            "text": "Verbs (Actions)",
            "emoji": "🏃",
            "children": [
              { "id": "v_v1", "text": "follow (遵循)", "emoji": "✅", "children": [] },
              { "id": "v_v2", "text": "arrive (到达)", "emoji": "📍", "children": [] },
              { "id": "v_v3", "text": "litter (乱扔)", "emoji": "🗑️", "children": [] },
              { "id": "v_v4", "text": "practise (训练)", "emoji": "🎹", "children": [] },
              { "id": "v_v5", "text": "relax (放松)", "emoji": "🏖️", "children": [] }
            ]
          },
          {
            "id": "v_n",
            "text": "Nouns (Things)",
            "emoji": "🎒",
            "children": [
              { "id": "v_n1", "text": "rule (规则)", "emoji": "📏", "children": [] },
              { "id": "v_n2", "text": "uniform (校服)", "emoji": "👕", "children": [] },
              { "id": "v_n3", "text": "hallway (走廊)", "emoji": "🚶", "children": [] },
              { "id": "v_n4", "text": "queue (队)", "emoji": "👫", "children": [] },
              { "id": "v_n5", "text": "spirit (精神)", "emoji": "🔥", "children": [] }
            ]
          },
          {
            "id": "v_p",
            "text": "Phrases (Expressions)",
            "emoji": "🗣️",
            "children": [
              { "id": "v_p1", "text": "on time (准时)", "emoji": "⏰", "children": [] },
              { "id": "v_p2", "text": "have to (不得不)", "emoji": "💪", "children": [] },
              { "id": "v_p3", "text": "hang out (闲逛)", "emoji": "🚶", "children": [] },
              { "id": "v_p4", "text": "focus on (集中于)", "emoji": "🎯", "children": [] },
              { "id": "v_p5", "text": "at weekends (在周末)", "emoji": "🗓️", "children": [] }
            ]
          }
        ]
      },
      {
        "id": "grammar",
        "text": "Grammar Focus",
        "emoji": "⚙️",
        "children": [
          {
            "id": "g1",
            "text": "Imperatives",
            "emoji": "📢",
            "children": [
              { "id": "g1_1", "text": "Walk in the hallway.", "emoji": "🚶", "children": [] },
              { "id": "g1_2", "text": "Don't run!", "emoji": "🚫", "children": [] }
            ]
          },
          {
            "id": "g2",
            "text": "Modal Verbs",
            "emoji": "💡",
            "children": [
              { "id": "g2_1", "text": "Can / Can't (Ability/Permission)", "emoji": "🙋", "children": [] },
              { "id": "g2_2", "text": "Must / Mustn't (Obligation)", "emoji": "❗", "children": [] },
              { "id": "g2_3", "text": "Have to (Necessity)", "emoji": "💼", "children": [] }
            ]
          }
        ]
      }
    ]
  }
}
