{
  "level": "RAZ Level B",
  "title": "Bonkers Likes to Bark",
  "unit_vocabulary": [
    {
      "id": "v1",
      "word": "bark",
      "meaning": "吠叫",
      "ipa": "/bɑːk/",
      "context_sentence": "Bonkers likes to bark.",
      "page_number": 3,
      "comparison": "bark vs dark",
      "syllable_type": "r控制音节 (R-Controlled)",
      "memorization_hook": "对着树皮（bark）大声吠叫（bark）"
    },
    {
      "id": "v2",
      "word": "cars",
      "meaning": "汽车",
      "ipa": "/kɑːz/",
      "context_sentence": "Bonkers likes to bark at cars.",
      "page_number": 4,
      "comparison": "cars vs cards",
      "syllable_type": "r控制音节 (R-Controlled)",
      "memorization_hook": "汽车（cars）卡（ca...）在路上"
    },
    {
      "id": "v3",
      "word": "cats",
      "meaning": "猫",
      "ipa": "/kæts/",
      "context_sentence": "Bonkers likes to bark at cats.",
      "page_number": 5,
      "comparison": "cats vs hats",
      "syllable_type": "闭音节 (Closed)",
      "memorization_hook": "猫咪（cats）喜欢开（ca...）心玩"
    },
    {
      "id": "v4",
      "word": "bikes",
      "meaning": "自行车",
      "ipa": "/baɪks/",
      "context_sentence": "Bonkers likes to bark at bikes.",
      "page_number": 6,
      "comparison": "bikes vs lakes",
      "syllable_type": "相对开音节 (VCe)",
      "memorization_hook": "骑自行车（bikes）摆（bi...）摆手"
    },
    {
      "id": "v5",
      "word": "squirrels",
      "meaning": "松鼠",
      "ipa": "/ˈskwɪrəlz/",
      "context_sentence": "Bonkers likes to bark at squirrels.",
      "page_number": 7,
      "comparison": "squirrels vs skirts",
      "syllable_type": "squir-rels",
      "memorization_hook": "松鼠（squirrels）死（squir...）守着松果"
    },
    {
      "id": "v6",
      "word": "kids",
      "meaning": "孩子们",
      "ipa": "/kɪdz/",
      "context_sentence": "Bonkers likes to bark at kids.",
      "page_number": 8,
      "comparison": "kids vs lids",
      "syllable_type": "闭音节 (Closed)",
      "memorization_hook": "孩子们（kids）开（ki...）心地笑"
    },
    {
      "id": "v7",
      "word": "birds",
      "meaning": "鸟",
      "ipa": "/bɜːdz/",
      "context_sentence": "Bonkers likes to bark at birds.",
      "page_number": 9,
      "comparison": "birds vs beds",
      "syllable_type": "r控制音节 (R-Controlled)",
      "memorization_hook": "鸟（birds）波（bi...）浪般飞过"
    },
    {
      "id": "v8",
      "word": "Bonkers",
      "meaning": "邦克斯",
      "ipa": "/ˈbɒŋkəz/",
      "context_sentence": "Bonkers likes to bark at Bonkers!",
      "page_number": 10,
      "comparison": "Bonkers vs bankers",
      "syllable_type": "Bon-kers",
      "memorization_hook": "蹦（Bon...）蹦跳跳的小狗叫邦克斯（Bonkers）"
    },
    {
      "id": "v9",
      "word": "likes to",
      "meaning": "喜欢",
      "ipa": "/laɪks tuː/",
      "context_sentence": "Bonkers likes to bark.",
      "page_number": 3,
      "comparison": "likes to vs likes",
      "syllable_type": "词组",
      "memorization_hook": "喜欢（likes to）做某事"
    },
    {
      "id": "v10",
      "word": "bark at",
      "meaning": "冲...叫",
      "ipa": "/bɑːk æt/",
      "context_sentence": "Bonkers likes to bark at cars.",
      "page_number": 4,
      "comparison": "bark at vs look at",
      "syllable_type": "词组",
      "memorization_hook": "冲（at）着...吠叫（bark）"
    }
  ]
}
